{
  "storagedrawers:recipes/storagedrawers/one_stack_upgrade": {
    "criteria": {
      "has_template": "2026-06-17 23:26:40 +0700"
    },
    "done": true
  },
  "create:root": {
    "criteria": {
      "0": "2026-06-17 23:26:40 +0700"
    },
    "done": true
  },
  "storagedrawers:recipes/storagedrawers/illumination_upgrade": {
    "criteria": {
      "has_template": "2026-06-17 23:26:40 +0700"
    },
    "done": true
  },
  "mekanism:root": {
    "criteria": {
      "automatic": "2026-06-17 23:26:40 +0700"
    },
    "done": true
  },
  "storagedrawers:recipes/storagedrawers/remote_upgrade": {
    "criteria": {
      "has_template": "2026-06-17 23:26:40 +0700"
    },
    "done": true
  },
  "storagedrawers:recipes/storagedrawers/personal_key_cofh": {
    "criteria": {
      "has_template": "2026-06-17 23:26:40 +0700"
    },
    "done": true
  },
  "storagedrawers:recipes/storagedrawers/acacia_trim": {
    "criteria": {
      "has_planks": "2026-06-17 23:26:40 +0700"
    },
    "done": true
  },
  "storagedrawers:recipes/storagedrawers/priority_key": {
    "criteria": {
      "has_template": "2026-06-17 23:26:40 +0700"
    },
    "done": true
  },
  "brewinandchewin:main/root": {
    "criteria": {
      "beer": "2026-06-17 23:26:40 +0700"
    },
    "done": true
  },
  "storagedrawers:recipes/storagedrawers/cherry_trim": {
    "criteria": {
      "has_planks": "2026-06-17 23:26:40 +0700"
    },
    "done": true
  },
  "storagedrawers:recipes/storagedrawers/gold_storage_upgrade": {
    "criteria": {
      "has_template": "2026-06-17 23:26:40 +0700"
    },
    "done": true
  },
  "storagedrawers:recipes/storagedrawers/birch_trim": {
    "criteria": {
      "has_planks": "2026-06-17 23:26:40 +0700"
    },
    "done": true
  },
  "storagedrawers:recipes/storagedrawers/void_upgrade": {
    "criteria": {
      "has_template": "2026-06-17 23:26:40 +0700"
    },
    "done": true
  },
  "storagedrawers:recipes/storagedrawers/fill_level_upgrade": {
    "criteria": {
      "has_template": "2026-06-17 23:26:40 +0700"
    },
    "done": true
  },
  "storagedrawers:recipes/storagedrawers/oak_trim": {
    "criteria": {
      "has_planks": "2026-06-17 23:26:40 +0700"
    },
    "done": true
  },
  "storagedrawers:recipes/storagedrawers/emerald_storage_upgrade": {
    "criteria": {
      "has_template": "2026-06-17 23:26:40 +0700"
    },
    "done": true
  },
  "storagedrawers:recipes/storagedrawers/obsidian_storage_upgrade": {
    "criteria": {
      "has_template": "2026-06-17 23:26:40 +0700"
    },
    "done": true
  },
  "storagedrawers:recipes/storagedrawers/iron_storage_upgrade": {
    "criteria": {
      "has_template": "2026-06-17 23:26:40 +0700"
    },
    "done": true
  },
  "storagedrawers:recipes/storagedrawers/diamond_storage_upgrade": {
    "criteria": {
      "has_template": "2026-06-17 23:26:40 +0700"
    },
    "done": true
  },
  "storagedrawers:recipes/storagedrawers/remote_group_upgrade": {
    "criteria": {
      "has_template": "2026-06-17 23:26:40 +0700"
    },
    "done": true
  },
  "storagedrawers:recipes/storagedrawers/drawer_puller": {
    "criteria": {
      "has_template": "2026-06-17 23:26:40 +0700"
    },
    "done": true
  },
  "storagedrawers:recipes/storagedrawers/crimson_trim": {
    "criteria": {
      "has_planks": "2026-06-17 23:26:40 +0700"
    },
    "done": true
  },
  "storagedrawers:recipes/storagedrawers/shroud_key": {
    "criteria": {
      "has_template": "2026-06-17 23:26:40 +0700"
    },
    "done": true
  },
  "storagedrawers:recipes/storagedrawers/portability_upgrade": {
    "criteria": {
      "has_template": "2026-06-17 23:26:40 +0700"
    },
    "done": true
  },
  "escalated:root": {
    "criteria": {
      "0": "2026-06-17 23:26:40 +0700"
    },
    "done": true
  },
  "storagedrawers:recipes/storagedrawers/drawer_key": {
    "criteria": {
      "has_template": "2026-06-17 23:26:40 +0700"
    },
    "done": true
  },
  "storagedrawers:recipes/storagedrawers/min_redstone_upgrade": {
    "criteria": {
      "has_template": "2026-06-17 23:26:40 +0700"
    },
    "done": true
  },
  "storagedrawers:recipes/storagedrawers/keyring": {
    "criteria": {
      "has_template": "2026-06-17 23:26:40 +0700"
    },
    "done": true
  },
  "storagedrawers:recipes/storagedrawers/personal_key": {
    "criteria": {
      "has_template": "2026-06-17 23:26:40 +0700"
    },
    "done": true
  },
  "storagedrawers:recipes/storagedrawers/warped_trim": {
    "criteria": {
      "has_planks": "2026-06-17 23:26:40 +0700"
    },
    "done": true
  },
  "storagedrawers:recipes/storagedrawers/jungle_trim": {
    "criteria": {
      "has_planks": "2026-06-17 23:26:40 +0700"
    },
    "done": true
  },
  "storagedrawers:recipes/storagedrawers/max_redstone_upgrade": {
    "criteria": {
      "has_template": "2026-06-17 23:26:40 +0700"
    },
    "done": true
  },
  "storagedrawers:recipes/storagedrawers/bamboo_trim": {
    "criteria": {
      "has_planks": "2026-06-17 23:26:40 +0700"
    },
    "done": true
  },
  "storagedrawers:recipes/storagedrawers/mangrove_trim": {
    "criteria": {
      "has_planks": "2026-06-17 23:26:40 +0700"
    },
    "done": true
  },
  "storagedrawers:recipes/storagedrawers/redstone_upgrade": {
    "criteria": {
      "has_template": "2026-06-17 23:26:40 +0700"
    },
    "done": true
  },
  "storagedrawers:recipes/storagedrawers/spruce_trim": {
    "criteria": {
      "has_planks": "2026-06-17 23:26:40 +0700"
    },
    "done": true
  },
  "farmersdelight:main/root": {
    "criteria": {
      "seeds": "2026-06-17 23:26:40 +0700"
    },
    "done": true
  },
  "storagedrawers:recipes/storagedrawers/quantify_key": {
    "criteria": {
      "has_template": "2026-06-17 23:26:40 +0700"
    },
    "done": true
  },
  "storagedrawers:recipes/storagedrawers/dark_oak_trim": {
    "criteria": {
      "has_planks": "2026-06-17 23:26:40 +0700"
    },
    "done": true
  },
  "storagedrawers:recipes/storagedrawers/balance_fill_upgrade": {
    "criteria": {
      "has_template": "2026-06-17 23:26:40 +0700"
    },
    "done": true
  },
  "minecraft:recipes/decorations/crafting_table": {
    "criteria": {
      "unlock_right_away": "2026-06-17 23:26:42 +0700"
    },
    "done": true
  },
  "refurbished_furniture:recipes/misc/constructing/green_stool": {
    "criteria": {
      "has_planks": "2026-06-17 23:27:23 +0700"
    },
    "done": true
  },
  "refurbished_furniture:recipes/misc/constructing/oak_kitchen_drawer": {
    "criteria": {
      "has_oak_planks": "2026-06-17 23:27:23 +0700"
    },
    "done": true
  },
  "refurbished_furniture:recipes/misc/constructing/red_lamp": {
    "criteria": {
      "has_planks": "2026-06-17 23:27:23 +0700"
    },
    "done": true
  },
  "refurbished_furniture:recipes/misc/constructing/yellow_sofa": {
    "criteria": {
      "has_planks": "2026-06-17 23:27:23 +0700"
    },
    "done": true
  },
  "refurbished_furniture:recipes/misc/constructing/orange_sofa": {
    "criteria": {
      "has_planks": "2026-06-17 23:27:23 +0700"
    },
    "done": true
  },
  "minecraft:recipes/misc/stick": {
    "criteria": {
      "has_planks": "2026-06-17 23:27:23 +0700"
    },
    "done": true
  },
  "refurbished_furniture:recipes/misc/constructing/oak_light_ceiling_fan": {
    "criteria": {
      "has_oak_planks": "2026-06-17 23:27:23 +0700"
    },
    "done": true
  },
  "refurbished_furniture:recipes/misc/constructing/magenta_stool": {
    "criteria": {
      "has_planks": "2026-06-17 23:27:23 +0700"
    },
    "done": true
  },
  "refurbished_furniture:recipes/misc/constructing/oak_drawer": {
    "criteria": {
      "has_oak_planks": "2026-06-17 23:27:23 +0700"
    },
    "done": true
  },
  "refurbished_furniture:recipes/misc/constructing/brown_cooler": {
    "criteria": {
      "has_planks": "2026-06-17 23:27:23 +0700"
    },
    "done": true
  },
  "refurbished_furniture:recipes/misc/constructing/cyan_cooler": {
    "criteria": {
      "has_planks": "2026-06-17 23:27:23 +0700"
    },
    "done": true
  },
  "refurbished_furniture:recipes/misc/constructing/lime_stool": {
    "criteria": {
      "has_planks": "2026-06-17 23:27:23 +0700"
    },
    "done": true
  },
  "minecraft:recipes/building_blocks/oak_slab": {
    "criteria": {
      "has_planks": "2026-06-17 23:27:23 +0700"
    },
    "done": true
  },
  "refurbished_furniture:recipes/misc/constructing/light_gray_sofa": {
    "criteria": {
      "has_planks": "2026-06-17 23:27:23 +0700"
    },
    "done": true
  },
  "refurbished_furniture:recipes/misc/constructing/oak_kitchen_cabinetry": {
    "criteria": {
      "has_oak_planks": "2026-06-17 23:27:23 +0700"
    },
    "done": true
  },
  "minecraft:recipes/redstone/oak_door": {
    "criteria": {
      "has_planks": "2026-06-17 23:27:23 +0700"
    },
    "done": true
  },
  "supplementaries:recipes/turn_table": {
    "criteria": {
      "minecraft:planks": "2026-06-17 23:27:23 +0700"
    },
    "done": true
  },
  "refurbished_furniture:recipes/misc/constructing/green_lamp": {
    "criteria": {
      "has_planks": "2026-06-17 23:27:23 +0700"
    },
    "done": true
  },
  "refurbished_furniture:recipes/misc/constructing/magenta_sofa": {
    "criteria": {
      "has_planks": "2026-06-17 23:27:23 +0700"
    },
    "done": true
  },
  "refurbished_furniture:recipes/misc/constructing/oak_storage_jar": {
    "criteria": {
      "has_oak_planks": "2026-06-17 23:27:23 +0700"
    },
    "done": true
  },
  "decorative_blocks:recipes/building_blocks/oak_seat": {
    "criteria": {
      "has_plank": "2026-06-17 23:27:23 +0700"
    },
    "done": true
  },
  "refurbished_furniture:recipes/misc/constructing/cyan_stool": {
    "criteria": {
      "has_planks": "2026-06-17 23:27:23 +0700"
    },
    "done": true
  },
  "refurbished_furniture:recipes/misc/constructing/brown_stool": {
    "criteria": {
      "has_planks": "2026-06-17 23:27:23 +0700"
    },
    "done": true
  },
  "minecraft:recipes/redstone/oak_trapdoor": {
    "criteria": {
      "has_planks": "2026-06-17 23:27:23 +0700"
    },
    "done": true
  },
  "refurbished_furniture:recipes/misc/constructing/lime_lamp": {
    "criteria": {
      "has_planks": "2026-06-17 23:27:23 +0700"
    },
    "done": true
  },
  "refurbished_furniture:recipes/misc/constructing/light_blue_cooler": {
    "criteria": {
      "has_planks": "2026-06-17 23:27:23 +0700"
    },
    "done": true
  },
  "refurbished_furniture:recipes/misc/constructing/oak_mail_box": {
    "criteria": {
      "has_oak_planks": "2026-06-17 23:27:23 +0700"
    },
    "done": true
  },
  "refurbished_furniture:recipes/misc/constructing/pink_sofa": {
    "criteria": {
      "has_planks": "2026-06-17 23:27:23 +0700"
    },
    "done": true
  },
  "refurbished_furniture:recipes/misc/constructing/oak_bath": {
    "criteria": {
      "has_oak_planks": "2026-06-17 23:27:23 +0700"
    },
    "done": true
  },
  "refurbished_furniture:recipes/misc/constructing/brown_lamp": {
    "criteria": {
      "has_planks": "2026-06-17 23:27:23 +0700"
    },
    "done": true
  },
  "supplementaries:recipes/bed_from_feather_block": {
    "criteria": {
      "minecraft:planks": "2026-06-17 23:27:23 +0700"
    },
    "done": true
  },
  "refurbished_furniture:recipes/misc/constructing/oak_basin": {
    "criteria": {
      "has_oak_planks": "2026-06-17 23:27:23 +0700"
    },
    "done": true
  },
  "refurbished_furniture:recipes/misc/workbench": {
    "criteria": {
      "has_planks": "2026-06-17 23:27:23 +0700"
    },
    "done": true
  },
  "refurbished_furniture:recipes/misc/constructing/light_blue_lamp": {
    "criteria": {
      "has_planks": "2026-06-17 23:27:23 +0700"
    },
    "done": true
  },
  "decorative_blocks:recipes/building_blocks/oak_support": {
    "criteria": {
      "has_plank": "2026-06-17 23:27:23 +0700"
    },
    "done": true
  },
  "refurbished_furniture:recipes/misc/constructing/blue_sofa": {
    "criteria": {
      "has_planks": "2026-06-17 23:27:23 +0700"
    },
    "done": true
  },
  "refurbished_furniture:recipes/misc/constructing/oak_chair": {
    "criteria": {
      "has_oak_planks": "2026-06-17 23:27:23 +0700"
    },
    "done": true
  },
  "supplementaries:recipes/notice_board": {
    "criteria": {
      "minecraft:planks": "2026-06-17 23:27:23 +0700"
    },
    "done": true
  },
  "refurbished_furniture:recipes/misc/constructing/gray_lamp": {
    "criteria": {
      "has_planks": "2026-06-17 23:27:23 +0700"
    },
    "done": true
  },
  "refurbished_furniture:recipes/misc/constructing/purple_sofa": {
    "criteria": {
      "has_planks": "2026-06-17 23:27:23 +0700"
    },
    "done": true
  },
  "refurbished_furniture:recipes/misc/constructing/oak_lattice_fence": {
    "criteria": {
      "has_oak_planks": "2026-06-17 23:27:23 +0700"
    },
    "done": true
  },
  "refurbished_furniture:recipes/misc/constructing/gray_cooler": {
    "criteria": {
      "has_planks": "2026-06-17 23:27:23 +0700"
    },
    "done": true
  },
  "minecraft:recipes/redstone/oak_pressure_plate": {
    "criteria": {
      "has_planks": "2026-06-17 23:27:23 +0700"
    },
    "done": true
  },
  "refurbished_furniture:recipes/misc/constructing/black_lamp": {
    "criteria": {
      "has_planks": "2026-06-17 23:27:23 +0700"
    },
    "done": true
  },
  "refurbished_furniture:recipes/misc/constructing/pink_cooler": {
    "criteria": {
      "has_planks": "2026-06-17 23:27:23 +0700"
    },
    "done": true
  },
  "refurbished_furniture:recipes/misc/constructing/cyan_sofa": {
    "criteria": {
      "has_planks": "2026-06-17 23:27:23 +0700"
    },
    "done": true
  },
  "refurbished_furniture:recipes/misc/constructing/black_stool": {
    "criteria": {
      "has_planks": "2026-06-17 23:27:23 +0700"
    },
    "done": true
  },
  "refurbished_furniture:recipes/misc/constructing/orange_cooler": {
    "criteria": {
      "has_planks": "2026-06-17 23:27:23 +0700"
    },
    "done": true
  },
  "refurbished_furniture:recipes/misc/constructing/pink_stool": {
    "criteria": {
      "has_planks": "2026-06-17 23:27:23 +0700"
    },
    "done": true
  },
  "refurbished_furniture:recipes/misc/constructing/purple_stool": {
    "criteria": {
      "has_planks": "2026-06-17 23:27:23 +0700"
    },
    "done": true
  },
  "refurbished_furniture:recipes/misc/constructing/oak_toilet": {
    "criteria": {
      "has_oak_planks": "2026-06-17 23:27:23 +0700"
    },
    "done": true
  },
  "refurbished_furniture:recipes/misc/constructing/yellow_lamp": {
    "criteria": {
      "has_planks": "2026-06-17 23:27:23 +0700"
    },
    "done": true
  },
  "minecraft:recipes/decorations/oak_sign": {
    "criteria": {
      "has_planks": "2026-06-17 23:27:23 +0700"
    },
    "done": true
  },
  "refurbished_furniture:recipes/misc/constructing/orange_lamp": {
    "criteria": {
      "has_planks": "2026-06-17 23:27:23 +0700"
    },
    "done": true
  },
  "supplementaries:recipes/lock_block": {
    "criteria": {
      "minecraft:planks": "2026-06-17 23:27:23 +0700"
    },
    "done": true
  },
  "refurbished_furniture:recipes/misc/constructing/white_lamp": {
    "criteria": {
      "has_planks": "2026-06-17 23:27:23 +0700"
    },
    "done": true
  },
  "refurbished_furniture:recipes/misc/constructing/oak_crate": {
    "criteria": {
      "has_oak_planks": "2026-06-17 23:27:23 +0700"
    },
    "done": true
  },
  "refurbished_furniture:recipes/misc/constructing/oak_lattice_fence_gate": {
    "criteria": {
      "has_oak_planks": "2026-06-17 23:27:23 +0700"
    },
    "done": true
  },
  "refurbished_furniture:recipes/misc/constructing/purple_cooler": {
    "criteria": {
      "has_planks": "2026-06-17 23:27:23 +0700"
    },
    "done": true
  },
  "refurbished_furniture:recipes/misc/constructing/light_gray_cooler": {
    "criteria": {
      "has_planks": "2026-06-17 23:27:23 +0700"
    },
    "done": true
  },
  "refurbished_furniture:recipes/misc/constructing/red_sofa": {
    "criteria": {
      "has_planks": "2026-06-17 23:27:23 +0700"
    },
    "done": true
  },
  "refurbished_furniture:recipes/misc/constructing/magenta_lamp": {
    "criteria": {
      "has_planks": "2026-06-17 23:27:23 +0700"
    },
    "done": true
  },
  "minecraft:recipes/redstone/oak_fence_gate": {
    "criteria": {
      "has_planks": "2026-06-17 23:27:23 +0700"
    },
    "done": true
  },
  "refurbished_furniture:recipes/misc/constructing/oak_kitchen_storage_cabinet": {
    "criteria": {
      "has_oak_planks": "2026-06-17 23:27:23 +0700"
    },
    "done": true
  },
  "refurbished_furniture:recipes/misc/constructing/oak_desk": {
    "criteria": {
      "has_oak_planks": "2026-06-17 23:27:23 +0700"
    },
    "done": true
  },
  "refurbished_furniture:recipes/misc/constructing/post_box": {
    "criteria": {
      "has_planks": "2026-06-17 23:27:23 +0700"
    },
    "done": true
  },
  "supplementaries:recipes/clock_block": {
    "criteria": {
      "minecraft:planks": "2026-06-17 23:27:23 +0700"
    },
    "done": true
  },
  "minecraft:recipes/decorations/barrel": {
    "criteria": {
      "has_planks": "2026-06-17 23:27:23 +0700"
    },
    "done": true
  },
  "refurbished_furniture:recipes/misc/constructing/oak_cutting_board": {
    "criteria": {
      "has_oak_planks": "2026-06-17 23:27:23 +0700"
    },
    "done": true
  },
  "refurbished_furniture:recipes/misc/constructing/green_sofa": {
    "criteria": {
      "has_planks": "2026-06-17 23:27:23 +0700"
    },
    "done": true
  },
  "refurbished_furniture:recipes/misc/constructing/light_gray_lamp": {
    "criteria": {
      "has_planks": "2026-06-17 23:27:23 +0700"
    },
    "done": true
  },
  "refurbished_furniture:recipes/misc/constructing/blue_stool": {
    "criteria": {
      "has_planks": "2026-06-17 23:27:23 +0700"
    },
    "done": true
  },
  "refurbished_furniture:recipes/misc/constructing/oak_kitchen_sink": {
    "criteria": {
      "has_oak_planks": "2026-06-17 23:27:23 +0700"
    },
    "done": true
  },
  "refurbished_furniture:recipes/misc/constructing/orange_stool": {
    "criteria": {
      "has_planks": "2026-06-17 23:27:23 +0700"
    },
    "done": true
  },
  "refurbished_furniture:recipes/misc/constructing/black_cooler": {
    "criteria": {
      "has_planks": "2026-06-17 23:27:23 +0700"
    },
    "done": true
  },
  "refurbished_furniture:recipes/misc/constructing/magenta_cooler": {
    "criteria": {
      "has_planks": "2026-06-17 23:27:23 +0700"
    },
    "done": true
  },
  "refurbished_furniture:recipes/misc/constructing/lime_sofa": {
    "criteria": {
      "has_planks": "2026-06-17 23:27:23 +0700"
    },
    "done": true
  },
  "minecraft:recipes/building_blocks/oak_stairs": {
    "criteria": {
      "has_planks": "2026-06-17 23:27:23 +0700"
    },
    "done": true
  },
  "refurbished_furniture:recipes/misc/constructing/red_cooler": {
    "criteria": {
      "has_planks": "2026-06-17 23:27:23 +0700"
    },
    "done": true
  },
  "minecraft:recipes/decorations/oak_fence": {
    "criteria": {
      "has_planks": "2026-06-17 23:27:23 +0700"
    },
    "done": true
  },
  "supplementaries:recipes/speaker_block": {
    "criteria": {
      "minecraft:planks": "2026-06-17 23:27:23 +0700"
    },
    "done": true
  },
  "refurbished_furniture:recipes/misc/constructing/green_cooler": {
    "criteria": {
      "has_planks": "2026-06-17 23:27:23 +0700"
    },
    "done": true
  },
  "refurbished_furniture:recipes/misc/constructing/brown_sofa": {
    "criteria": {
      "has_planks": "2026-06-17 23:27:23 +0700"
    },
    "done": true
  },
  "refurbished_furniture:recipes/misc/constructing/light_blue_stool": {
    "criteria": {
      "has_planks": "2026-06-17 23:27:23 +0700"
    },
    "done": true
  },
  "minecraft:recipes/redstone/oak_button": {
    "criteria": {
      "has_planks": "2026-06-17 23:27:23 +0700"
    },
    "done": true
  },
  "refurbished_furniture:recipes/misc/constructing/white_cooler": {
    "criteria": {
      "has_planks": "2026-06-17 23:27:23 +0700"
    },
    "done": true
  },
  "refurbished_furniture:recipes/misc/constructing/blue_lamp": {
    "criteria": {
      "has_planks": "2026-06-17 23:27:23 +0700"
    },
    "done": true
  },
  "refurbished_furniture:recipes/misc/constructing/red_stool": {
    "criteria": {
      "has_planks": "2026-06-17 23:27:23 +0700"
    },
    "done": true
  },
  "refurbished_furniture:recipes/misc/constructing/light_blue_sofa": {
    "criteria": {
      "has_planks": "2026-06-17 23:27:23 +0700"
    },
    "done": true
  },
  "refurbished_furniture:recipes/misc/constructing/black_sofa": {
    "criteria": {
      "has_planks": "2026-06-17 23:27:23 +0700"
    },
    "done": true
  },
  "refurbished_furniture:recipes/misc/constructing/light_gray_stool": {
    "criteria": {
      "has_planks": "2026-06-17 23:27:23 +0700"
    },
    "done": true
  },
  "refurbished_furniture:recipes/misc/constructing/white_stool": {
    "criteria": {
      "has_planks": "2026-06-17 23:27:23 +0700"
    },
    "done": true
  },
  "refurbished_furniture:recipes/misc/constructing/yellow_stool": {
    "criteria": {
      "has_planks": "2026-06-17 23:27:23 +0700"
    },
    "done": true
  },
  "refurbished_furniture:recipes/misc/constructing/pink_lamp": {
    "criteria": {
      "has_planks": "2026-06-17 23:27:23 +0700"
    },
    "done": true
  },
  "refurbished_furniture:recipes/misc/constructing/lime_cooler": {
    "criteria": {
      "has_planks": "2026-06-17 23:27:23 +0700"
    },
    "done": true
  },
  "refurbished_furniture:recipes/misc/constructing/oak_storage_cabinet": {
    "criteria": {
      "has_oak_planks": "2026-06-17 23:27:23 +0700"
    },
    "done": true
  },
  "refurbished_furniture:recipes/misc/constructing/gray_stool": {
    "criteria": {
      "has_planks": "2026-06-17 23:27:23 +0700"
    },
    "done": true
  },
  "create:recipes/building_blocks/oak_window": {
    "criteria": {
      "has_ingredient": "2026-06-17 23:27:23 +0700"
    },
    "done": true
  },
  "refurbished_furniture:recipes/misc/constructing/white_sofa": {
    "criteria": {
      "has_planks": "2026-06-17 23:27:23 +0700"
    },
    "done": true
  },
  "refurbished_furniture:recipes/misc/constructing/oak_table": {
    "criteria": {
      "has_oak_planks": "2026-06-17 23:27:23 +0700"
    },
    "done": true
  },
  "supplementaries:recipes/pulley": {
    "criteria": {
      "minecraft:planks": "2026-06-17 23:27:23 +0700"
    },
    "done": true
  },
  "refurbished_furniture:recipes/misc/constructing/yellow_cooler": {
    "criteria": {
      "has_planks": "2026-06-17 23:27:23 +0700"
    },
    "done": true
  },
  "refurbished_furniture:recipes/misc/constructing/blue_cooler": {
    "criteria": {
      "has_planks": "2026-06-17 23:27:23 +0700"
    },
    "done": true
  },
  "refurbished_furniture:recipes/misc/constructing/cyan_lamp": {
    "criteria": {
      "has_planks": "2026-06-17 23:27:23 +0700"
    },
    "done": true
  },
  "refurbished_furniture:recipes/misc/constructing/gray_sofa": {
    "criteria": {
      "has_planks": "2026-06-17 23:27:23 +0700"
    },
    "done": true
  },
  "refurbished_furniture:recipes/misc/constructing/purple_lamp": {
    "criteria": {
      "has_planks": "2026-06-17 23:27:23 +0700"
    },
    "done": true
  },
  "minecraft:recipes/decorations/ladder": {
    "criteria": {
      "has_stick": "2026-06-17 23:35:34 +0700"
    },
    "done": true
  },
  "antiblocksrechiseled:recipes/building_blocks/wool_orange": {
    "criteria": {
      "has_wool": "2026-06-17 23:57:56 +0700"
    },
    "done": true
  },
  "decorative_blocks:recipes/building_blocks/spruce_support": {
    "criteria": {
      "has_plank": "2026-06-17 23:38:11 +0700"
    },
    "done": true
  },
  "supplementaries:recipes/decorations/sign_post_acacia": {
    "criteria": {
      "has_item": "2026-06-17 23:52:24 +0700"
    },
    "done": true
  },
  "refurbished_furniture:recipes/misc/constructing/spruce_table": {
    "criteria": {
      "has_spruce_planks": "2026-06-17 23:38:11 +0700"
    },
    "done": true
  },
  "create:recipes/building_blocks/crafting/logistics/yellow_table_cloth": {
    "criteria": {
      "has_wool": "2026-06-17 23:39:39 +0700"
    },
    "done": true
  },
  "decorative_blocks:recipes/building_blocks/crimson_support": {
    "criteria": {
      "has_plank": "2026-06-17 23:52:06 +0700"
    },
    "done": true
  },
  "minecraft:recipes/redstone/birch_button": {
    "criteria": {
      "has_planks": "2026-06-17 23:52:08 +0700"
    },
    "done": true
  },
  "tconstruct:recipes/misc/tables/pattern": {
    "criteria": {
      "has_item": "2026-06-17 23:35:34 +0700"
    },
    "done": true
  },
  "berry_good:recipes/decorations/sweet_berry_basket": {
    "criteria": {
      "has_sweet_berries": "2026-06-18 00:27:47 +0700"
    },
    "done": true
  },
  "refurbished_furniture:recipes/misc/constructing/birch_cutting_board": {
    "criteria": {
      "has_birch_planks": "2026-06-17 23:52:08 +0700"
    },
    "done": true
  },
  "create:recipes/building_blocks/dark_oak_window": {
    "criteria": {
      "has_ingredient": "2026-06-18 00:48:47 +0700"
    },
    "done": true
  },
  "berry_good:recipes/food/sweet_berry_mince": {
    "criteria": {
      "has_sweet_berries": "2026-06-18 00:27:47 +0700"
    },
    "done": true
  },
  "supplementaries:recipes/flags/flag_magenta": {
    "criteria": {
      "has_stick": "2026-06-17 23:35:34 +0700"
    },
    "done": true
  },
  "refurbished_furniture:recipes/misc/constructing/acacia_table": {
    "criteria": {
      "has_acacia_planks": "2026-06-17 23:52:24 +0700"
    },
    "done": true
  },
  "refurbished_furniture:recipes/misc/constructing/acacia_storage_jar": {
    "criteria": {
      "has_acacia_planks": "2026-06-17 23:52:24 +0700"
    },
    "done": true
  },
  "refurbished_furniture:recipes/misc/constructing/dark_oak_kitchen_cabinetry": {
    "criteria": {
      "has_dark_oak_planks": "2026-06-18 00:48:47 +0700"
    },
    "done": true
  },
  "refurbished_furniture:recipes/misc/constructing/acacia_mail_box": {
    "criteria": {
      "has_acacia_planks": "2026-06-17 23:52:24 +0700"
    },
    "done": true
  },
  "minecraft:recipes/decorations/birch_fence": {
    "criteria": {
      "has_planks": "2026-06-17 23:52:08 +0700"
    },
    "done": true
  },
  "minecraft:recipes/tools/wooden_axe": {
    "criteria": {
      "has_stick": "2026-06-17 23:35:34 +0700"
    },
    "done": true
  },
  "antiblocksrechiseled:recipes/building_blocks/wool_brown": {
    "criteria": {
      "has_wool": "2026-06-17 23:57:56 +0700"
    },
    "done": true
  },
  "refurbished_furniture:recipes/misc/constructing/spruce_kitchen_drawer": {
    "criteria": {
      "has_spruce_planks": "2026-06-17 23:38:11 +0700"
    },
    "done": true
  },
  "create:recipes/building_blocks/crafting/kinetics/blue_seat": {
    "criteria": {
      "has_wool": "2026-06-17 23:39:39 +0700"
    },
    "done": true
  },
  "refurbished_furniture:recipes/misc/constructing/dark_oak_crate": {
    "criteria": {
      "has_dark_oak_planks": "2026-06-18 00:48:47 +0700"
    },
    "done": true
  },
  "mekanism:moving_blocks": {
    "criteria": {
      "cardboard_box": "2026-06-18 01:05:13 +0700"
    },
    "done": false
  },
  "antiblocksrechiseled:recipes/building_blocks/wool_pink": {
    "criteria": {
      "has_wool": "2026-06-17 23:57:56 +0700"
    },
    "done": true
  },
  "minecraft:recipes/decorations/chest": {
    "criteria": {
      "has_lots_of_items": "2026-06-17 23:38:02 +0700"
    },
    "done": true
  },
  "supplementaries:recipes/decorations/sign_post_dark_oak": {
    "criteria": {
      "has_item": "2026-06-18 00:48:47 +0700"
    },
    "done": true
  },
  "minecraft:recipes/redstone/crimson_pressure_plate": {
    "criteria": {
      "has_planks": "2026-06-17 23:52:06 +0700"
    },
    "done": true
  },
  "xercapaint:recipes/item_easel": {
    "criteria": {
      "has_item": "2026-06-17 23:35:34 +0700"
    },
    "done": true
  },
  "minecraft:recipes/decorations/birch_sign": {
    "criteria": {
      "has_planks": "2026-06-17 23:52:08 +0700"
    },
    "done": true
  },
  "refurbished_furniture:recipes/misc/constructing/birch_bath": {
    "criteria": {
      "has_birch_planks": "2026-06-17 23:52:08 +0700"
    },
    "done": true
  },
  "create:recipes/building_blocks/crafting/kinetics/light_blue_seat": {
    "criteria": {
      "has_wool": "2026-06-17 23:39:39 +0700"
    },
    "done": true
  },
  "refurbished_furniture:recipes/misc/constructing/dark_oak_kitchen_sink": {
    "criteria": {
      "has_dark_oak_planks": "2026-06-18 00:48:47 +0700"
    },
    "done": true
  },
  "refurbished_furniture:recipes/misc/constructing/crimson_light_ceiling_fan": {
    "criteria": {
      "has_crimson_planks": "2026-06-17 23:52:06 +0700"
    },
    "done": true
  },
  "refurbished_furniture:recipes/misc/constructing/dark_oak_drawer": {
    "criteria": {
      "has_dark_oak_planks": "2026-06-18 00:48:47 +0700"
    },
    "done": true
  },
  "minecraft:recipes/building_blocks/clay": {
    "criteria": {
      "has_clay_ball": "2026-06-18 00:14:51 +0700"
    },
    "done": true
  },
  "minecraft:recipes/redstone/tripwire_hook": {
    "criteria": {
      "has_string": "2026-06-17 23:44:11 +0700"
    },
    "done": true
  },
  "create:recipes/building_blocks/crafting/logistics/orange_postbox": {
    "criteria": {
      "has_barrel": "2026-06-18 00:08:19 +0700"
    },
    "done": true
  },
  "refurbished_furniture:recipes/misc/constructing/birch_toilet": {
    "criteria": {
      "has_birch_planks": "2026-06-17 23:52:08 +0700"
    },
    "done": true
  },
  "decorative_blocks:recipes/building_blocks/birch_seat": {
    "criteria": {
      "has_plank": "2026-06-17 23:52:08 +0700"
    },
    "done": true
  },
  "refurbished_furniture:recipes/misc/constructing/crimson_basin": {
    "criteria": {
      "has_crimson_planks": "2026-06-17 23:52:06 +0700"
    },
    "done": true
  },
  "supplementaries:recipes/decorations/sign_post_crimson": {
    "criteria": {
      "has_item": "2026-06-17 23:52:06 +0700"
    },
    "done": true
  },
  "minecraft:recipes/building_blocks/acacia_stairs": {
    "criteria": {
      "has_planks": "2026-06-17 23:52:24 +0700"
    },
    "done": true
  },
  "refurbished_furniture:recipes/misc/constructing/dark_oak_cutting_board": {
    "criteria": {
      "has_dark_oak_planks": "2026-06-18 00:48:47 +0700"
    },
    "done": true
  },
  "minecraft:recipes/decorations/candle": {
    "criteria": {
      "has_string": "2026-06-17 23:44:11 +0700"
    },
    "done": true
  },
  "minecraft:recipes/building_blocks/birch_slab": {
    "criteria": {
      "has_planks": "2026-06-17 23:52:08 +0700"
    },
    "done": true
  },
  "refurbished_furniture:recipes/misc/constructing/dark_oak_kitchen_drawer": {
    "criteria": {
      "has_dark_oak_planks": "2026-06-18 00:48:47 +0700"
    },
    "done": true
  },
  "refurbished_furniture:recipes/misc/constructing/birch_lattice_fence": {
    "criteria": {
      "has_stick": "2026-06-17 23:35:34 +0700"
    },
    "done": true
  },
  "refurbished_furniture:recipes/misc/constructing/spruce_light_ceiling_fan": {
    "criteria": {
      "has_spruce_planks": "2026-06-17 23:38:11 +0700"
    },
    "done": true
  },
  "create:recipes/building_blocks/crafting/logistics/cyan_table_cloth": {
    "criteria": {
      "has_wool": "2026-06-17 23:39:39 +0700"
    },
    "done": true
  },
  "minecraft:recipes/building_blocks/dark_oak_stairs": {
    "criteria": {
      "has_planks": "2026-06-18 00:48:47 +0700"
    },
    "done": true
  },
  "farmersdelight:main/plant_all_crops": {
    "criteria": {
      "sweet_berries": "2026-06-18 00:15:13 +0700"
    },
    "done": false
  },
  "refurbished_furniture:recipes/misc/constructing/crimson_chair": {
    "criteria": {
      "has_crimson_planks": "2026-06-17 23:52:06 +0700"
    },
    "done": true
  },
  "refurbished_furniture:recipes/misc/constructing/dark_oak_mail_box": {
    "criteria": {
      "has_dark_oak_planks": "2026-06-18 00:48:47 +0700"
    },
    "done": true
  },
  "refurbished_furniture:recipes/misc/constructing/jungle_kitchen_drawer": {
    "criteria": {
      "has_jungle_planks": "2026-06-17 23:32:13 +0700"
    },
    "done": true
  },
  "create:recipes/building_blocks/crafting/logistics/red_table_cloth": {
    "criteria": {
      "has_wool": "2026-06-17 23:39:39 +0700"
    },
    "done": true
  },
  "supplementaries:recipes/daub_cross_brace": {
    "criteria": {
      "forge:rods/wooden": "2026-06-17 23:35:34 +0700"
    },
    "done": true
  },
  "refurbished_furniture:recipes/misc/constructing/dark_oak_storage_jar": {
    "criteria": {
      "has_dark_oak_planks": "2026-06-18 00:48:47 +0700"
    },
    "done": true
  },
  "minecraft:recipes/building_blocks/jungle_stairs": {
    "criteria": {
      "has_planks": "2026-06-17 23:32:13 +0700"
    },
    "done": true
  },
  "create:recipes/building_blocks/crimson_window": {
    "criteria": {
      "has_ingredient": "2026-06-17 23:52:06 +0700"
    },
    "done": true
  },
  "refurbished_furniture:recipes/misc/constructing/jungle_kitchen_cabinetry": {
    "criteria": {
      "has_jungle_planks": "2026-06-17 23:32:13 +0700"
    },
    "done": true
  },
  "minecraft:recipes/redstone/spruce_button": {
    "criteria": {
      "has_planks": "2026-06-17 23:38:11 +0700"
    },
    "done": true
  },
  "refurbished_furniture:recipes/misc/constructing/jungle_desk": {
    "criteria": {
      "has_jungle_planks": "2026-06-17 23:32:13 +0700"
    },
    "done": true
  },
  "minecraft:recipes/redstone/dark_oak_door": {
    "criteria": {
      "has_planks": "2026-06-18 00:48:47 +0700"
    },
    "done": true
  },
  "refurbished_furniture:recipes/misc/constructing/crimson_mail_box": {
    "criteria": {
      "has_crimson_planks": "2026-06-17 23:52:06 +0700"
    },
    "done": true
  },
  "refurbished_furniture:recipes/misc/constructing/acacia_storage_cabinet": {
    "criteria": {
      "has_acacia_planks": "2026-06-17 23:52:24 +0700"
    },
    "done": true
  },
  "decorative_blocks:recipes/building_blocks/lattice": {
    "criteria": {
      "has_stick": "2026-06-17 23:35:34 +0700"
    },
    "done": true
  },
  "create:recipes/building_blocks/acacia_window": {
    "criteria": {
      "has_ingredient": "2026-06-17 23:52:24 +0700"
    },
    "done": true
  },
  "minecraft:recipes/decorations/acacia_sign": {
    "criteria": {
      "has_planks": "2026-06-17 23:52:24 +0700"
    },
    "done": true
  },
  "refurbished_furniture:recipes/misc/constructing/jungle_crate": {
    "criteria": {
      "has_jungle_planks": "2026-06-17 23:32:13 +0700"
    },
    "done": true
  },
  "minecraft:recipes/decorations/campfire": {
    "criteria": {
      "has_stick": "2026-06-17 23:35:34 +0700"
    },
    "done": true
  },
  "supplementaries:recipes/sign_post_jungle": {
    "criteria": {
      "has_the_recipe": "2026-06-17 23:32:13 +0700"
    },
    "done": true
  },
  "refurbished_furniture:recipes/misc/constructing/dark_oak_lattice_fence": {
    "criteria": {
      "has_stick": "2026-06-17 23:35:34 +0700"
    },
    "done": true
  },
  "refurbished_furniture:recipes/misc/constructing/jungle_storage_cabinet": {
    "criteria": {
      "has_jungle_planks": "2026-06-17 23:32:13 +0700"
    },
    "done": true
  },
  "minecraft:recipes/redstone/jungle_trapdoor": {
    "criteria": {
      "has_planks": "2026-06-17 23:32:13 +0700"
    },
    "done": true
  },
  "create:recipes/building_blocks/crafting/logistics/gray_postbox": {
    "criteria": {
      "has_barrel": "2026-06-18 00:08:19 +0700"
    },
    "done": true
  },
  "berry_good:recipes/misc/sweet_berry_pips": {
    "criteria": {
      "has_sweet_berries": "2026-06-18 00:27:47 +0700"
    },
    "done": true
  },
  "supplementaries:recipes/timber_brace": {
    "criteria": {
      "forge:rods/wooden": "2026-06-17 23:35:34 +0700"
    },
    "done": true
  },
  "refurbished_furniture:recipes/misc/constructing/jungle_light_ceiling_fan": {
    "criteria": {
      "has_jungle_planks": "2026-06-17 23:32:13 +0700"
    },
    "done": true
  },
  "minecraft:recipes/decorations/jungle_sign": {
    "criteria": {
      "has_planks": "2026-06-17 23:32:13 +0700"
    },
    "done": true
  },
  "create:recipes/misc/crafting/appliances/book": {
    "criteria": {
      "has_item": "2026-06-18 01:05:30 +0700"
    },
    "done": true
  },
  "immersiveengineering:recipes/misc/crafting/alloybrick": {
    "criteria": {
      "has_brick": "2026-06-18 01:02:01 +0700"
    },
    "done": true
  },
  "refurbished_furniture:recipes/misc/constructing/acacia_kitchen_drawer": {
    "criteria": {
      "has_acacia_planks": "2026-06-17 23:52:24 +0700"
    },
    "done": true
  },
  "refurbished_furniture:recipes/misc/constructing/birch_storage_jar": {
    "criteria": {
      "has_birch_planks": "2026-06-17 23:52:08 +0700"
    },
    "done": true
  },
  "refurbished_furniture:recipes/misc/constructing/acacia_kitchen_storage_cabinet": {
    "criteria": {
      "has_acacia_planks": "2026-06-17 23:52:24 +0700"
    },
    "done": true
  },
  "create:recipes/misc/crafting/appliances/cardboard_leggings": {
    "criteria": {
      "has_item": "2026-06-18 01:05:30 +0700"
    },
    "done": true
  },
  "minecraft:recipes/misc/brick": {
    "criteria": {
      "has_clay_ball": "2026-06-18 00:14:51 +0700"
    },
    "done": true
  },
  "decorative_blocks:recipes/building_blocks/dark_oak_support": {
    "criteria": {
      "has_plank": "2026-06-18 00:48:47 +0700"
    },
    "done": true
  },
  "minecraft:recipes/decorations/jungle_fence": {
    "criteria": {
      "has_planks": "2026-06-17 23:32:13 +0700"
    },
    "done": true
  },
  "supplementaries:recipes/flags/flag_black": {
    "criteria": {
      "has_stick": "2026-06-17 23:35:34 +0700"
    },
    "done": true
  },
  "refurbished_furniture:recipes/misc/constructing/crimson_storage_jar": {
    "criteria": {
      "has_crimson_planks": "2026-06-17 23:52:06 +0700"
    },
    "done": true
  },
  "minecraft:recipes/combat/wooden_sword": {
    "criteria": {
      "has_stick": "2026-06-17 23:35:34 +0700"
    },
    "done": true
  },
  "refurbished_furniture:recipes/misc/constructing/crimson_desk": {
    "criteria": {
      "has_crimson_planks": "2026-06-17 23:52:06 +0700"
    },
    "done": true
  },
  "supplementaries:recipes/flags/flag_green": {
    "criteria": {
      "has_stick": "2026-06-17 23:35:34 +0700"
    },
    "done": true
  },
  "farmersdelight:recipes/food/sweet_berry_cookie": {
    "criteria": {
      "has_sweet_berries": "2026-06-18 00:27:47 +0700"
    },
    "done": true
  },
  "create:recipes/misc/crafting/kinetics/nozzle": {
    "criteria": {
      "has_item": "2026-06-18 00:12:39 +0700"
    },
    "done": true
  },
  "refurbished_furniture:recipes/misc/constructing/jungle_toilet": {
    "criteria": {
      "has_jungle_planks": "2026-06-17 23:32:13 +0700"
    },
    "done": true
  },
  "refurbished_furniture:recipes/misc/constructing/jungle_table": {
    "criteria": {
      "has_jungle_planks": "2026-06-17 23:32:13 +0700"
    },
    "done": true
  },
  "supplementaries:recipes/flags/flag_purple": {
    "criteria": {
      "has_stick": "2026-06-17 23:35:34 +0700"
    },
    "done": true
  },
  "refurbished_furniture:recipes/misc/constructing/birch_light_ceiling_fan": {
    "criteria": {
      "has_birch_planks": "2026-06-17 23:52:08 +0700"
    },
    "done": true
  },
  "refurbished_furniture:recipes/misc/constructing/birch_desk": {
    "criteria": {
      "has_birch_planks": "2026-06-17 23:52:08 +0700"
    },
    "done": true
  },
  "create:recipes/misc/crafting/appliances/cardboard_sword": {
    "criteria": {
      "has_item": "2026-06-18 01:05:30 +0700"
    },
    "done": true
  },
  "create:recipes/building_blocks/jungle_window": {
    "criteria": {
      "has_ingredient": "2026-06-17 23:32:13 +0700"
    },
    "done": true
  },
  "create:recipes/building_blocks/crafting/logistics/lime_postbox": {
    "criteria": {
      "has_barrel": "2026-06-18 00:08:19 +0700"
    },
    "done": true
  },
  "miners_delight:recipes/food/weird_caviar": {
    "criteria": {
      "has_silverfish_eggs": "2026-06-17 23:46:02 +0700"
    },
    "done": true
  },
  "create:recipes/building_blocks/crafting/logistics/purple_table_cloth": {
    "criteria": {
      "has_wool": "2026-06-17 23:39:39 +0700"
    },
    "done": true
  },
  "supplementaries:recipes/flags/flag_white": {
    "criteria": {
      "has_stick": "2026-06-17 23:35:34 +0700"
    },
    "done": true
  },
  "refurbished_furniture:recipes/misc/constructing/jungle_lattice_fence_gate": {
    "criteria": {
      "has_jungle_planks": "2026-06-17 23:32:13 +0700"
    },
    "done": true
  },
  "refurbished_furniture:recipes/misc/constructing/magenta_trampoline": {
    "criteria": {
      "has_string": "2026-06-17 23:44:11 +0700"
    },
    "done": true
  },
  "fairylights:recipes/fairylights/tinsel_garland": {
    "criteria": {
      "has_string": "2026-06-17 23:44:11 +0700"
    },
    "done": true
  },
  "supplementaries:recipes/timber_cross_brace": {
    "criteria": {
      "forge:rods/wooden": "2026-06-17 23:35:34 +0700"
    },
    "done": true
  },
  "refurbished_furniture:recipes/misc/constructing/dark_oak_chair": {
    "criteria": {
      "has_dark_oak_planks": "2026-06-18 00:48:47 +0700"
    },
    "done": true
  },
  "create:encased_fan": {
    "criteria": {
      "0": "2026-06-18 00:13:44 +0700"
    },
    "done": true
  },
  "supplementaries:recipes/sign_post_dark_oak": {
    "criteria": {
      "has_the_recipe": "2026-06-18 00:48:47 +0700"
    },
    "done": true
  },
  "minecraft:recipes/redstone/acacia_pressure_plate": {
    "criteria": {
      "has_planks": "2026-06-17 23:52:24 +0700"
    },
    "done": true
  },
  "minecraft:recipes/building_blocks/crimson_slab": {
    "criteria": {
      "has_planks": "2026-06-17 23:52:06 +0700"
    },
    "done": true
  },
  "refurbished_furniture:recipes/misc/constructing/spruce_kitchen_cabinetry": {
    "criteria": {
      "has_spruce_planks": "2026-06-17 23:38:11 +0700"
    },
    "done": true
  },
  "antiblocksrechiseled:recipes/building_blocks/wool_cyan": {
    "criteria": {
      "has_wool": "2026-06-17 23:57:56 +0700"
    },
    "done": true
  },
  "antiblocksrechiseled:recipes/building_blocks/wool_green": {
    "criteria": {
      "has_wool": "2026-06-17 23:57:56 +0700"
    },
    "done": true
  },
  "refurbished_furniture:recipes/misc/constructing/acacia_drawer": {
    "criteria": {
      "has_acacia_planks": "2026-06-17 23:52:24 +0700"
    },
    "done": true
  },
  "decorative_blocks:recipes/building_blocks/spruce_seat": {
    "criteria": {
      "has_plank": "2026-06-17 23:38:11 +0700"
    },
    "done": true
  },
  "create:recipes/misc/crafting/appliances/cardboard_helmet": {
    "criteria": {
      "has_item": "2026-06-18 01:05:30 +0700"
    },
    "done": true
  },
  "refurbished_furniture:recipes/misc/constructing/dark_oak_basin": {
    "criteria": {
      "has_dark_oak_planks": "2026-06-18 00:48:47 +0700"
    },
    "done": true
  },
  "supplementaries:recipes/flags/flag_gray": {
    "criteria": {
      "has_stick": "2026-06-17 23:35:34 +0700"
    },
    "done": true
  },
  "immersiveengineering:recipes/misc/crafting/cokebrick": {
    "criteria": {
      "has_item": "2026-06-18 00:14:51 +0700"
    },
    "done": true
  },
  "minecraft:recipes/combat/bow": {
    "criteria": {
      "has_string": "2026-06-17 23:44:11 +0700"
    },
    "done": true
  },
  "minecraft:recipes/building_blocks/acacia_slab": {
    "criteria": {
      "has_planks": "2026-06-17 23:52:24 +0700"
    },
    "done": true
  },
  "supplementaries:recipes/faucet": {
    "criteria": {
      "forge:rods/wooden": "2026-06-17 23:35:34 +0700"
    },
    "done": true
  },
  "antiblocksrechiseled:recipes/building_blocks/wool_yellow": {
    "criteria": {
      "has_wool": "2026-06-17 23:57:56 +0700"
    },
    "done": true
  },
  "create:recipes/misc/crafting/logistics/package_frogport": {
    "criteria": {
      "has_item": "2026-06-18 01:05:30 +0700"
    },
    "done": true
  },
  "minecraft:recipes/decorations/spruce_sign": {
    "criteria": {
      "has_planks": "2026-06-17 23:38:11 +0700"
    },
    "done": true
  },
  "refurbished_furniture:recipes/misc/constructing/spruce_lattice_fence": {
    "criteria": {
      "has_stick": "2026-06-17 23:35:34 +0700"
    },
    "done": true
  },
  "create:recipes/building_blocks/crafting/kinetics/red_seat": {
    "criteria": {
      "has_wool": "2026-06-17 23:39:39 +0700"
    },
    "done": true
  },
  "create:recipes/building_blocks/crafting/kinetics/light_gray_seat": {
    "criteria": {
      "has_wool": "2026-06-17 23:39:39 +0700"
    },
    "done": true
  },
  "decorative_blocks:recipes/building_blocks/birch_support": {
    "criteria": {
      "has_plank": "2026-06-17 23:52:08 +0700"
    },
    "done": true
  },
  "fairylights:recipes/fairylights/letter_bunting": {
    "criteria": {
      "has_string": "2026-06-17 23:44:11 +0700"
    },
    "done": true
  },
  "minecraft:recipes/decorations/composter": {
    "criteria": {
      "has_wood_slab": "2026-06-18 00:08:14 +0700"
    },
    "done": true
  },
  "antiblocksrechiseled:recipes/building_blocks/wool_red": {
    "criteria": {
      "has_wool": "2026-06-17 23:57:56 +0700"
    },
    "done": true
  },
  "refurbished_furniture:recipes/misc/constructing/crimson_lattice_fence_gate": {
    "criteria": {
      "has_stick": "2026-06-17 23:35:34 +0700"
    },
    "done": true
  },
  "minecraft:recipes/decorations/smoker": {
    "criteria": {
      "has_furnace": "2026-06-18 00:51:17 +0700"
    },
    "done": true
  },
  "create:recipes/building_blocks/crafting/logistics/blue_table_cloth": {
    "criteria": {
      "has_wool": "2026-06-17 23:39:39 +0700"
    },
    "done": true
  },
  "supplementaries:recipes/bamboo_spikes": {
    "criteria": {
      "minecraft:wooden_slabs": "2026-06-18 00:08:14 +0700"
    },
    "done": true
  },
  "minecraft:recipes/building_blocks/sponge": {
    "criteria": {
      "has_wet_sponge": "2026-06-17 23:59:10 +0700"
    },
    "done": true
  },
  "enderio:recipes/misc/wood_gear": {
    "criteria": {
      "has_ingredient": "2026-06-17 23:35:34 +0700"
    },
    "done": true
  },
  "refurbished_furniture:recipes/misc/constructing/light_gray_trampoline": {
    "criteria": {
      "has_string": "2026-06-17 23:44:11 +0700"
    },
    "done": true
  },
  "refurbished_furniture:recipes/misc/constructing/dark_oak_table": {
    "criteria": {
      "has_dark_oak_planks": "2026-06-18 00:48:47 +0700"
    },
    "done": true
  },
  "refurbished_furniture:recipes/misc/constructing/green_trampoline": {
    "criteria": {
      "has_string": "2026-06-17 23:44:11 +0700"
    },
    "done": true
  },
  "create:recipes/misc/crafting/logistics/redstone_requester": {
    "criteria": {
      "has_item": "2026-06-18 01:05:30 +0700"
    },
    "done": true
  },
  "supplementaries:recipes/decorations/sign_post_jungle": {
    "criteria": {
      "has_item": "2026-06-17 23:32:13 +0700"
    },
    "done": true
  },
  "create:recipes/misc/crafting/appliances/name_tag": {
    "criteria": {
      "has_item": "2026-06-18 01:05:30 +0700"
    },
    "done": true
  },
  "create:recipes/building_blocks/crafting/logistics/light_gray_table_cloth": {
    "criteria": {
      "has_wool": "2026-06-17 23:39:39 +0700"
    },
    "done": true
  },
  "refurbished_furniture:recipes/misc/constructing/crimson_kitchen_cabinetry": {
    "criteria": {
      "has_crimson_planks": "2026-06-17 23:52:06 +0700"
    },
    "done": true
  },
  "supplementaries:recipes/decorations/sign_post_spruce": {
    "criteria": {
      "has_item": "2026-06-17 23:38:11 +0700"
    },
    "done": true
  },
  "supplementaries:recipes/flags/flag_light_blue": {
    "criteria": {
      "has_stick": "2026-06-17 23:35:34 +0700"
    },
    "done": true
  },
  "refurbished_furniture:recipes/misc/constructing/acacia_desk": {
    "criteria": {
      "has_acacia_planks": "2026-06-17 23:52:24 +0700"
    },
    "done": true
  },
  "refurbished_furniture:recipes/misc/knife": {
    "criteria": {
      "has_string": "2026-06-17 23:44:11 +0700"
    },
    "done": true
  },
  "create:recipes/building_blocks/crafting/kinetics/cyan_seat": {
    "criteria": {
      "has_wool": "2026-06-17 23:39:39 +0700"
    },
    "done": true
  },
  "supplementaries:recipes/blackboard": {
    "criteria": {
      "minecraft:wooden_slabs": "2026-06-18 00:08:14 +0700"
    },
    "done": true
  },
  "create:recipes/misc/crafting/appliances/cardboard_chestplate": {
    "criteria": {
      "has_item": "2026-06-18 01:05:30 +0700"
    },
    "done": true
  },
  "farmersdelight:recipes/decorations/skillet": {
    "criteria": {
      "has_brick": "2026-06-18 01:02:01 +0700"
    },
    "done": true
  },
  "antiblocksrechiseled:recipes/building_blocks/wool_white": {
    "criteria": {
      "has_wool": "2026-06-17 23:57:56 +0700"
    },
    "done": true
  },
  "create:recipes/building_blocks/crafting/logistics/white_postbox": {
    "criteria": {
      "has_barrel": "2026-06-18 00:08:19 +0700"
    },
    "done": true
  },
  "minecraft:recipes/redstone/dark_oak_pressure_plate": {
    "criteria": {
      "has_planks": "2026-06-18 00:48:47 +0700"
    },
    "done": true
  },
  "immersiveengineering:main/main_root": {
    "criteria": {
      "has_item": "2026-06-18 01:02:11 +0700"
    },
    "done": true
  },
  "minecraft:recipes/decorations/decorated_pot_simple": {
    "criteria": {
      "has_brick": "2026-06-18 01:02:01 +0700"
    },
    "done": true
  },
  "supplementaries:recipes/sign_post_acacia": {
    "criteria": {
      "has_the_recipe": "2026-06-17 23:52:24 +0700"
    },
    "done": true
  },
  "minecraft:recipes/building_blocks/dark_oak_slab": {
    "criteria": {
      "has_planks": "2026-06-18 00:48:47 +0700"
    },
    "done": true
  },
  "refurbished_furniture:recipes/misc/constructing/spruce_toilet": {
    "criteria": {
      "has_spruce_planks": "2026-06-17 23:38:11 +0700"
    },
    "done": true
  },
  "supplementaries:recipes/daub_brace": {
    "criteria": {
      "forge:rods/wooden": "2026-06-17 23:35:34 +0700"
    },
    "done": true
  },
  "refurbished_furniture:recipes/misc/wrench": {
    "criteria": {
      "has_string": "2026-06-17 23:44:11 +0700"
    },
    "done": true
  },
  "antiblocksrechiseled:recipes/building_blocks/wool_gray": {
    "criteria": {
      "has_wool": "2026-06-17 23:57:56 +0700"
    },
    "done": true
  },
  "botania:recipes/food/mushroom_stew": {
    "criteria": {
      "has_item": "2026-06-17 23:47:15 +0700"
    },
    "done": true
  },
  "immersiveengineering:recipes/misc/crafting/alloybrick_to_slab": {
    "criteria": {
      "has_alloybrick": "2026-06-18 01:02:07 +0700"
    },
    "done": true
  },
  "create:recipes/building_blocks/crafting/kinetics/pink_seat": {
    "criteria": {
      "has_wool": "2026-06-17 23:39:39 +0700"
    },
    "done": true
  },
  "refurbished_furniture:recipes/misc/constructing/pink_trampoline": {
    "criteria": {
      "has_string": "2026-06-17 23:44:11 +0700"
    },
    "done": true
  },
  "refurbished_furniture:recipes/misc/constructing/birch_drawer": {
    "criteria": {
      "has_birch_planks": "2026-06-17 23:52:08 +0700"
    },
    "done": true
  },
  "refurbished_furniture:recipes/misc/constructing/birch_table": {
    "criteria": {
      "has_birch_planks": "2026-06-17 23:52:08 +0700"
    },
    "done": true
  },
  "immersiveengineering:recipes/misc/crafting/concrete": {
    "criteria": {
      "has_clay": "2026-06-18 00:14:51 +0700"
    },
    "done": true
  },
  "create:recipes/building_blocks/crafting/logistics/black_table_cloth": {
    "criteria": {
      "has_wool": "2026-06-17 23:39:39 +0700"
    },
    "done": true
  },
  "immersiveengineering:recipes/misc/crafting/survey_tools": {
    "criteria": {
      "has_hammer": "2026-06-18 00:52:24 +0700"
    },
    "done": true
  },
  "ceramicbucket:recipes/misc/unfired_clay_bucket": {
    "criteria": {
      "has_clay": "2026-06-18 00:14:51 +0700"
    },
    "done": true
  },
  "refurbished_furniture:recipes/misc/constructing/birch_kitchen_storage_cabinet": {
    "criteria": {
      "has_birch_planks": "2026-06-17 23:52:08 +0700"
    },
    "done": true
  },
  "minecraft:recipes/tools/wooden_pickaxe": {
    "criteria": {
      "has_stick": "2026-06-17 23:35:34 +0700"
    },
    "done": true
  },
  "farmersdelight:recipes/food/mixed_salad": {
    "criteria": {
      "has_bowl": "2026-06-17 23:47:15 +0700"
    },
    "done": true
  },
  "supplementaries:recipes/flags/flag_cyan": {
    "criteria": {
      "has_stick": "2026-06-17 23:35:34 +0700"
    },
    "done": true
  },
  "create:recipes/building_blocks/crafting/logistics/pink_table_cloth": {
    "criteria": {
      "has_wool": "2026-06-17 23:39:39 +0700"
    },
    "done": true
  },
  "refurbished_furniture:recipes/misc/constructing/cherry_lattice_fence_gate": {
    "criteria": {
      "has_stick": "2026-06-17 23:35:34 +0700"
    },
    "done": true
  },
  "supplementaries:recipes/candle_holders/candle_holder": {
    "criteria": {
      "has_candle": "2026-06-18 00:38:11 +0700"
    },
    "done": true
  },
  "create:recipes/misc/crafting/appliances/cardboard_boots": {
    "criteria": {
      "has_item": "2026-06-18 01:05:30 +0700"
    },
    "done": true
  },
  "minecraft:recipes/redstone/birch_trapdoor": {
    "criteria": {
      "has_planks": "2026-06-17 23:52:08 +0700"
    },
    "done": true
  },
  "minecraft:recipes/redstone/spruce_trapdoor": {
    "criteria": {
      "has_planks": "2026-06-17 23:38:11 +0700"
    },
    "done": true
  },
  "immersiveengineering:recipes/misc/crafting/fluid_sorter": {
    "criteria": {
      "has_fluid_pipe": "2026-06-17 23:35:48 +0700"
    },
    "done": true
  },
  "minecraft:recipes/decorations/acacia_fence": {
    "criteria": {
      "has_planks": "2026-06-17 23:52:24 +0700"
    },
    "done": true
  },
  "create:recipes/building_blocks/crafting/logistics/brown_table_cloth": {
    "criteria": {
      "has_wool": "2026-06-17 23:39:39 +0700"
    },
    "done": true
  },
  "minecraft:recipes/redstone/jungle_pressure_plate": {
    "criteria": {
      "has_planks": "2026-06-17 23:32:13 +0700"
    },
    "done": true
  },
  "enderio:recipes/misc/conduit_binder_composite": {
    "criteria": {
      "has_ingredient_clay": "2026-06-18 00:14:51 +0700"
    },
    "done": true
  },
  "create:recipes/building_blocks/crafting/logistics/pink_postbox": {
    "criteria": {
      "has_barrel": "2026-06-18 00:08:19 +0700"
    },
    "done": true
  },
  "supplementaries:recipes/flags/flag_red": {
    "criteria": {
      "has_stick": "2026-06-17 23:35:34 +0700"
    },
    "done": true
  },
  "create:recipes/misc/crafting/logistics/packager": {
    "criteria": {
      "has_item": "2026-06-18 01:05:30 +0700"
    },
    "done": true
  },
  "create:recipes/building_blocks/crafting/logistics/black_postbox": {
    "criteria": {
      "has_barrel": "2026-06-18 00:08:19 +0700"
    },
    "done": true
  },
  "create:recipes/misc/crafting/appliances/item_frame": {
    "criteria": {
      "has_item": "2026-06-18 01:05:30 +0700"
    },
    "done": true
  },
  "minecraft:adventure/kill_a_mob": {
    "criteria": {
      "minecraft:silverfish": "2026-06-17 23:45:32 +0700"
    },
    "done": true
  },
  "create:recipes/misc/crafting/logistics/stock_ticker": {
    "criteria": {
      "has_item": "2026-06-18 01:05:30 +0700"
    },
    "done": true
  },
  "create:fan_processing": {
    "criteria": {
      "0": "2026-06-18 00:14:49 +0700"
    },
    "done": true
  },
  "refurbished_furniture:recipes/misc/constructing/jungle_kitchen_storage_cabinet": {
    "criteria": {
      "has_jungle_planks": "2026-06-17 23:32:13 +0700"
    },
    "done": true
  },
  "minecraft:recipes/food/mushroom_stew": {
    "criteria": {
      "has_bowl": "2026-06-17 23:47:15 +0700"
    },
    "done": true
  },
  "refurbished_furniture:recipes/frying/sweet_berry_jam": {
    "criteria": {
      "has_ingredient": "2026-06-18 00:27:47 +0700"
    },
    "done": true
  },
  "supplementaries:recipes/daub": {
    "criteria": {
      "has_clay_ball": "2026-06-18 00:14:51 +0700"
    },
    "done": true
  },
  "create:recipes/building_blocks/crafting/logistics/red_postbox": {
    "criteria": {
      "has_barrel": "2026-06-18 00:08:19 +0700"
    },
    "done": true
  },
  "refurbished_furniture:recipes/misc/constructing/warped_lattice_fence": {
    "criteria": {
      "has_stick": "2026-06-17 23:35:34 +0700"
    },
    "done": true
  },
  "refurbished_furniture:recipes/misc/constructing/dark_oak_light_ceiling_fan": {
    "criteria": {
      "has_dark_oak_planks": "2026-06-18 00:48:47 +0700"
    },
    "done": true
  },
  "create:cardboard_armor": {
    "criteria": {
      "0": "2026-06-18 01:06:30 +0700"
    },
    "done": true
  },
  "refurbished_furniture:recipes/misc/constructing/birch_lattice_fence_gate": {
    "criteria": {
      "has_stick": "2026-06-17 23:35:34 +0700"
    },
    "done": true
  },
  "fairylights:recipes/fairylights/triangle_pennant": {
    "criteria": {
      "has_string": "2026-06-17 23:44:11 +0700"
    },
    "done": true
  },
  "minecraft:recipes/redstone/acacia_button": {
    "criteria": {
      "has_planks": "2026-06-17 23:52:24 +0700"
    },
    "done": true
  },
  "create:recipes/building_blocks/birch_window": {
    "criteria": {
      "has_ingredient": "2026-06-17 23:52:08 +0700"
    },
    "done": true
  },
  "supplementaries:recipes/soap/map": {
    "criteria": {
      "has_soap": "2026-06-18 00:13:08 +0700"
    },
    "done": true
  },
  "minecraft:recipes/decorations/brown_banner": {
    "criteria": {
      "has_brown_wool": "2026-06-17 23:39:39 +0700"
    },
    "done": true
  },
  "refurbished_furniture:recipes/misc/constructing/crimson_lattice_fence": {
    "criteria": {
      "has_stick": "2026-06-17 23:35:34 +0700"
    },
    "done": true
  },
  "refurbished_furniture:recipes/misc/constructing/birch_crate": {
    "criteria": {
      "has_birch_planks": "2026-06-17 23:52:08 +0700"
    },
    "done": true
  },
  "refurbished_furniture:recipes/misc/constructing/crimson_kitchen_drawer": {
    "criteria": {
      "has_crimson_planks": "2026-06-17 23:52:06 +0700"
    },
    "done": true
  },
  "refurbished_furniture:recipes/misc/constructing/jungle_lattice_fence": {
    "criteria": {
      "has_jungle_planks": "2026-06-17 23:32:13 +0700"
    },
    "done": true
  },
  "refurbished_furniture:recipes/misc/constructing/spruce_lattice_fence_gate": {
    "criteria": {
      "has_stick": "2026-06-17 23:35:34 +0700"
    },
    "done": true
  },
  "create:recipes/building_blocks/crafting/logistics/brown_postbox": {
    "criteria": {
      "has_barrel": "2026-06-18 00:08:19 +0700"
    },
    "done": true
  },
  "create:recipes/building_blocks/crafting/logistics/lime_table_cloth": {
    "criteria": {
      "has_wool": "2026-06-17 23:39:39 +0700"
    },
    "done": true
  },
  "minecraft:recipes/decorations/brown_bed": {
    "criteria": {
      "has_brown_wool": "2026-06-17 23:39:39 +0700"
    },
    "done": true
  },
  "supplementaries:recipes/crank": {
    "criteria": {
      "forge:rods/wooden": "2026-06-17 23:35:34 +0700"
    },
    "done": true
  },
  "refurbished_furniture:recipes/misc/constructing/spruce_kitchen_sink": {
    "criteria": {
      "has_spruce_planks": "2026-06-17 23:38:11 +0700"
    },
    "done": true
  },
  "refurbished_furniture:recipes/misc/constructing/dark_oak_toilet": {
    "criteria": {
      "has_dark_oak_planks": "2026-06-18 00:48:47 +0700"
    },
    "done": true
  },
  "refurbished_furniture:recipes/misc/spatula": {
    "criteria": {
      "has_string": "2026-06-17 23:44:11 +0700"
    },
    "done": true
  },
  "refurbished_furniture:recipes/misc/constructing/acacia_bath": {
    "criteria": {
      "has_acacia_planks": "2026-06-17 23:52:24 +0700"
    },
    "done": true
  },
  "create:recipes/building_blocks/crafting/logistics/green_table_cloth": {
    "criteria": {
      "has_wool": "2026-06-17 23:39:39 +0700"
    },
    "done": true
  },
  "supplementaries:recipes/soap_block": {
    "criteria": {
      "has_soap": "2026-06-18 00:13:08 +0700"
    },
    "done": true
  },
  "refurbished_furniture:recipes/misc/constructing/crimson_storage_cabinet": {
    "criteria": {
      "has_crimson_planks": "2026-06-17 23:52:06 +0700"
    },
    "done": true
  },
  "refurbished_furniture:recipes/misc/slicing/red_dye_from_sweet_berries": {
    "criteria": {
      "has_sweet_berries": "2026-06-18 00:27:47 +0700"
    },
    "done": true
  },
  "refurbished_furniture:recipes/misc/constructing/dark_oak_lattice_fence_gate": {
    "criteria": {
      "has_stick": "2026-06-17 23:35:34 +0700"
    },
    "done": true
  },
  "create:recipes/building_blocks/crafting/logistics/magenta_postbox": {
    "criteria": {
      "has_barrel": "2026-06-18 00:08:19 +0700"
    },
    "done": true
  },
  "decorative_blocks:recipes/building_blocks/jungle_seat": {
    "criteria": {
      "has_plank": "2026-06-17 23:32:13 +0700"
    },
    "done": true
  },
  "supplementaries:recipes/flags/flag_orange": {
    "criteria": {
      "has_stick": "2026-06-17 23:35:34 +0700"
    },
    "done": true
  },
  "refurbished_furniture:recipes/misc/constructing/crimson_toilet": {
    "criteria": {
      "has_crimson_planks": "2026-06-17 23:52:06 +0700"
    },
    "done": true
  },
  "refurbished_furniture:recipes/misc/constructing/birch_kitchen_sink": {
    "criteria": {
      "has_birch_planks": "2026-06-17 23:52:08 +0700"
    },
    "done": true
  },
  "immersiveengineering:recipes/misc/crafting/torch": {
    "criteria": {
      "has_stick": "2026-06-17 23:35:34 +0700"
    },
    "done": true
  },
  "refurbished_furniture:recipes/misc/constructing/orange_trampoline": {
    "criteria": {
      "has_string": "2026-06-17 23:44:11 +0700"
    },
    "done": true
  },
  "refurbished_furniture:recipes/misc/constructing/cyan_trampoline": {
    "criteria": {
      "has_string": "2026-06-17 23:44:11 +0700"
    },
    "done": true
  },
  "minecraft:recipes/redstone/birch_door": {
    "criteria": {
      "has_planks": "2026-06-17 23:52:08 +0700"
    },
    "done": true
  },
  "create:recipes/misc/crafting/materials/cardboard_from_bound_block": {
    "criteria": {
      "has_item": "2026-06-18 01:05:30 +0700"
    },
    "done": true
  },
  "create:recipes/building_blocks/crafting/logistics/orange_table_cloth": {
    "criteria": {
      "has_wool": "2026-06-17 23:39:39 +0700"
    },
    "done": true
  },
  "refurbished_furniture:recipes/misc/constructing/dark_oak_storage_cabinet": {
    "criteria": {
      "has_dark_oak_planks": "2026-06-18 00:48:47 +0700"
    },
    "done": true
  },
  "decorative_blocks:recipes/building_blocks/jungle_support": {
    "criteria": {
      "has_plank": "2026-06-17 23:32:13 +0700"
    },
    "done": true
  },
  "create:recipes/misc/crafting/appliances/crafting_blueprint": {
    "criteria": {
      "has_item": "2026-06-17 23:32:16 +0700"
    },
    "done": true
  },
  "create:recipes/building_blocks/crafting/kinetics/magenta_seat": {
    "criteria": {
      "has_wool": "2026-06-17 23:39:39 +0700"
    },
    "done": true
  },
  "create:recipes/building_blocks/crafting/logistics/light_blue_postbox": {
    "criteria": {
      "has_barrel": "2026-06-18 00:08:19 +0700"
    },
    "done": true
  },
  "supplementaries:recipes/cage": {
    "criteria": {
      "minecraft:wooden_slabs": "2026-06-18 00:08:14 +0700"
    },
    "done": true
  },
  "refurbished_furniture:recipes/misc/constructing/jungle_storage_jar": {
    "criteria": {
      "has_jungle_planks": "2026-06-17 23:32:13 +0700"
    },
    "done": true
  },
  "refurbished_furniture:recipes/misc/constructing/spruce_kitchen_storage_cabinet": {
    "criteria": {
      "has_spruce_planks": "2026-06-17 23:38:11 +0700"
    },
    "done": true
  },
  "refurbished_furniture:recipes/misc/constructing/birch_kitchen_drawer": {
    "criteria": {
      "has_birch_planks": "2026-06-17 23:52:08 +0700"
    },
    "done": true
  },
  "minecraft:adventure/kill_all_mobs": {
    "criteria": {
      "minecraft:silverfish": "2026-06-17 23:45:32 +0700"
    },
    "done": false
  },
  "minecraft:recipes/decorations/crimson_sign": {
    "criteria": {
      "has_planks": "2026-06-17 23:52:06 +0700"
    },
    "done": true
  },
  "supplementaries:recipes/soap/spike": {
    "criteria": {
      "has_soap": "2026-06-18 00:13:08 +0700"
    },
    "done": true
  },
  "refurbished_furniture:recipes/misc/constructing/brown_trampoline": {
    "criteria": {
      "has_string": "2026-06-17 23:44:11 +0700"
    },
    "done": true
  },
  "refurbished_furniture:recipes/misc/constructing/spruce_bath": {
    "criteria": {
      "has_spruce_planks": "2026-06-17 23:38:11 +0700"
    },
    "done": true
  },
  "refurbished_furniture:recipes/misc/constructing/birch_storage_cabinet": {
    "criteria": {
      "has_birch_planks": "2026-06-17 23:52:08 +0700"
    },
    "done": true
  },
  "minecraft:recipes/redstone/birch_fence_gate": {
    "criteria": {
      "has_planks": "2026-06-17 23:52:08 +0700"
    },
    "done": true
  },
  "refurbished_furniture:recipes/misc/constructing/acacia_light_ceiling_fan": {
    "criteria": {
      "has_acacia_planks": "2026-06-17 23:52:24 +0700"
    },
    "done": true
  },
  "supplementaries:recipes/bomb": {
    "criteria": {
      "has_string": "2026-06-17 23:44:11 +0700"
    },
    "done": true
  },
  "refurbished_furniture:recipes/misc/constructing/light_blue_trampoline": {
    "criteria": {
      "has_string": "2026-06-17 23:44:11 +0700"
    },
    "done": true
  },
  "refurbished_furniture:recipes/misc/constructing/spruce_storage_jar": {
    "criteria": {
      "has_spruce_planks": "2026-06-17 23:38:11 +0700"
    },
    "done": true
  },
  "immersiveengineering:recipes/misc/crafting/fluid_pump": {
    "criteria": {
      "has_fluid_pipe": "2026-06-17 23:35:48 +0700"
    },
    "done": true
  },
  "refurbished_furniture:recipes/misc/constructing/acacia_cutting_board": {
    "criteria": {
      "has_acacia_planks": "2026-06-17 23:52:24 +0700"
    },
    "done": true
  },
  "refurbished_furniture:recipes/misc/constructing/jungle_cutting_board": {
    "criteria": {
      "has_jungle_planks": "2026-06-17 23:32:13 +0700"
    },
    "done": true
  },
  "create:recipes/building_blocks/crafting/logistics/green_postbox": {
    "criteria": {
      "has_barrel": "2026-06-18 00:08:19 +0700"
    },
    "done": true
  },
  "refurbished_furniture:recipes/misc/constructing/acacia_chair": {
    "criteria": {
      "has_acacia_planks": "2026-06-17 23:52:24 +0700"
    },
    "done": true
  },
  "minecraft:recipes/redstone/crimson_door": {
    "criteria": {
      "has_planks": "2026-06-17 23:52:06 +0700"
    },
    "done": true
  },
  "minecraft:recipes/redstone/acacia_door": {
    "criteria": {
      "has_planks": "2026-06-17 23:52:24 +0700"
    },
    "done": true
  },
  "minecraft:recipes/decorations/spruce_fence": {
    "criteria": {
      "has_planks": "2026-06-17 23:38:11 +0700"
    },
    "done": true
  },
  "create:recipes/building_blocks/spruce_window": {
    "criteria": {
      "has_ingredient": "2026-06-17 23:38:11 +0700"
    },
    "done": true
  },
  "supplementaries:recipes/decorations/sign_post_birch": {
    "criteria": {
      "has_item": "2026-06-17 23:52:08 +0700"
    },
    "done": true
  },
  "refurbished_furniture:recipes/misc/constructing/red_trampoline": {
    "criteria": {
      "has_string": "2026-06-17 23:44:11 +0700"
    },
    "done": true
  },
  "antiblocksrechiseled:recipes/building_blocks/wool_purple": {
    "criteria": {
      "has_wool": "2026-06-17 23:57:56 +0700"
    },
    "done": true
  },
  "minecraft:recipes/building_blocks/birch_stairs": {
    "criteria": {
      "has_planks": "2026-06-17 23:52:08 +0700"
    },
    "done": true
  },
  "refurbished_furniture:recipes/misc/constructing/blue_trampoline": {
    "criteria": {
      "has_string": "2026-06-17 23:44:11 +0700"
    },
    "done": true
  },
  "supplementaries:recipes/planter_rich": {
    "criteria": {
      "has_brick": "2026-06-18 01:02:01 +0700"
    },
    "done": true
  },
  "supplementaries:recipes/sign_post_spruce": {
    "criteria": {
      "has_the_recipe": "2026-06-17 23:38:11 +0700"
    },
    "done": true
  },
  "refurbished_furniture:recipes/misc/constructing/spruce_mail_box": {
    "criteria": {
      "has_spruce_planks": "2026-06-17 23:38:11 +0700"
    },
    "done": true
  },
  "refurbished_furniture:recipes/misc/constructing/acacia_basin": {
    "criteria": {
      "has_acacia_planks": "2026-06-17 23:52:24 +0700"
    },
    "done": true
  },
  "refurbished_furniture:recipes/misc/constructing/crimson_table": {
    "criteria": {
      "has_crimson_planks": "2026-06-17 23:52:06 +0700"
    },
    "done": true
  },
  "brewinandchewin:recipes/cooking/sweet_berry_jam": {
    "criteria": {
      "has_sweet_berries": "2026-06-18 00:27:47 +0700"
    },
    "done": true
  },
  "supplementaries:recipes/flags/flag_pink": {
    "criteria": {
      "has_stick": "2026-06-17 23:35:34 +0700"
    },
    "done": true
  },
  "minecraft:recipes/redstone/spruce_pressure_plate": {
    "criteria": {
      "has_planks": "2026-06-17 23:38:11 +0700"
    },
    "done": true
  },
  "refurbished_furniture:recipes/misc/constructing/spruce_crate": {
    "criteria": {
      "has_spruce_planks": "2026-06-17 23:38:11 +0700"
    },
    "done": true
  },
  "create:recipes/misc/crafting/materials/cardboard_from_block": {
    "criteria": {
      "has_the_recipe": "2026-06-18 01:05:29 +0700"
    },
    "done": true
  },
  "supplementaries:recipes/timber_frame": {
    "criteria": {
      "forge:rods/wooden": "2026-06-17 23:35:34 +0700"
    },
    "done": true
  },
  "supplementaries:recipes/soap/piston": {
    "criteria": {
      "has_soap": "2026-06-18 00:13:08 +0700"
    },
    "done": true
  },
  "minecraft:recipes/tools/wooden_hoe": {
    "criteria": {
      "has_stick": "2026-06-17 23:35:34 +0700"
    },
    "done": true
  },
  "supplementaries:recipes/sign_post_crimson": {
    "criteria": {
      "has_the_recipe": "2026-06-17 23:52:06 +0700"
    },
    "done": true
  },
  "refurbished_furniture:recipes/misc/constructing/acacia_lattice_fence": {
    "criteria": {
      "has_stick": "2026-06-17 23:35:34 +0700"
    },
    "done": true
  },
  "create:recipes/misc/crafting/materials/bound_cardboard_block": {
    "criteria": {
      "has_item": "2026-06-18 01:05:30 +0700"
    },
    "done": true
  },
  "enderio:recipes/misc/wood_gear_corner": {
    "criteria": {
      "has_ingredient": "2026-06-17 23:35:34 +0700"
    },
    "done": true
  },
  "refurbished_furniture:recipes/misc/constructing/white_trampoline": {
    "criteria": {
      "has_string": "2026-06-17 23:44:11 +0700"
    },
    "done": true
  },
  "supplementaries:recipes/slingshot": {
    "criteria": {
      "forge:rods/wooden": "2026-06-17 23:35:34 +0700"
    },
    "done": true
  },
  "refurbished_furniture:recipes/misc/constructing/birch_kitchen_cabinetry": {
    "criteria": {
      "has_birch_planks": "2026-06-17 23:52:08 +0700"
    },
    "done": true
  },
  "refurbished_furniture:recipes/misc/constructing/acacia_kitchen_sink": {
    "criteria": {
      "has_acacia_planks": "2026-06-17 23:52:24 +0700"
    },
    "done": true
  },
  "create:recipes/misc/crafting/materials/cardboard_block": {
    "criteria": {
      "has_item": "2026-06-18 01:05:30 +0700"
    },
    "done": true
  },
  "fairylights:recipes/fairylights/spearhead_pennant": {
    "criteria": {
      "has_string": "2026-06-17 23:44:11 +0700"
    },
    "done": true
  },
  "immersiveengineering:main/craft_hammer": {
    "criteria": {
      "has_item": "2026-06-18 00:52:24 +0700"
    },
    "done": true
  },
  "minecraft:recipes/redstone/jungle_door": {
    "criteria": {
      "has_planks": "2026-06-17 23:32:13 +0700"
    },
    "done": true
  },
  "tconstruct:recipes/building_blocks/smeltery/seared/grout": {
    "criteria": {
      "has_item": "2026-06-18 00:14:51 +0700"
    },
    "done": true
  },
  "decorative_blocks:recipes/building_blocks/crimson_seat": {
    "criteria": {
      "has_plank": "2026-06-17 23:52:06 +0700"
    },
    "done": true
  },
  "minecraft:recipes/tools/wooden_shovel": {
    "criteria": {
      "has_stick": "2026-06-17 23:35:34 +0700"
    },
    "done": true
  },
  "minecraft:recipes/decorations/crimson_fence": {
    "criteria": {
      "has_planks": "2026-06-17 23:52:06 +0700"
    },
    "done": true
  },
  "minecraft:adventure/root": {
    "criteria": {
      "killed_something": "2026-06-17 23:45:32 +0700"
    },
    "done": true
  },
  "supplementaries:recipes/item_shelf": {
    "criteria": {
      "minecraft:wooden_slabs": "2026-06-18 00:08:14 +0700"
    },
    "done": true
  },
  "minecraft:recipes/combat/crossbow": {
    "criteria": {
      "has_string": "2026-06-17 23:44:11 +0700"
    },
    "done": true
  },
  "create:recipes/building_blocks/crafting/kinetics/green_seat": {
    "criteria": {
      "has_wool": "2026-06-17 23:39:39 +0700"
    },
    "done": true
  },
  "farmersdelight:main/craft_knife": {
    "criteria": {
      "flint_knife": "2026-06-17 23:38:40 +0700"
    },
    "done": true
  },
  "create:recipes/building_blocks/crafting/kinetics/purple_seat": {
    "criteria": {
      "has_wool": "2026-06-17 23:39:39 +0700"
    },
    "done": true
  },
  "minecraft:recipes/decorations/white_bed": {
    "criteria": {
      "has_white_wool": "2026-06-17 23:57:56 +0700"
    },
    "done": true
  },
  "create:recipes/building_blocks/crafting/logistics/cyan_postbox": {
    "criteria": {
      "has_barrel": "2026-06-18 00:08:19 +0700"
    },
    "done": true
  },
  "create:recipes/building_blocks/crafting/logistics/yellow_postbox": {
    "criteria": {
      "has_barrel": "2026-06-18 00:08:19 +0700"
    },
    "done": true
  },
  "refurbished_furniture:recipes/misc/constructing/jungle_kitchen_sink": {
    "criteria": {
      "has_jungle_planks": "2026-06-17 23:32:13 +0700"
    },
    "done": true
  },
  "refurbished_furniture:recipes/misc/constructing/crimson_kitchen_storage_cabinet": {
    "criteria": {
      "has_crimson_planks": "2026-06-17 23:52:06 +0700"
    },
    "done": true
  },
  "fairylights:recipes/fairylights/swallowtail_pennant": {
    "criteria": {
      "has_string": "2026-06-17 23:44:11 +0700"
    },
    "done": true
  },
  "antiblocksrechiseled:recipes/building_blocks/wool_light_blue": {
    "criteria": {
      "has_wool": "2026-06-17 23:57:56 +0700"
    },
    "done": true
  },
  "supplementaries:recipes/sack": {
    "criteria": {
      "has_string": "2026-06-17 23:44:11 +0700"
    },
    "done": true
  },
  "minecraft:recipes/decorations/dark_oak_sign": {
    "criteria": {
      "has_planks": "2026-06-18 00:48:47 +0700"
    },
    "done": true
  },
  "refurbished_furniture:recipes/misc/constructing/yellow_trampoline": {
    "criteria": {
      "has_string": "2026-06-17 23:44:11 +0700"
    },
    "done": true
  },
  "refurbished_furniture:recipes/misc/constructing/mangrove_lattice_fence_gate": {
    "criteria": {
      "has_stick": "2026-06-17 23:35:34 +0700"
    },
    "done": true
  },
  "minecraft:recipes/building_blocks/jungle_slab": {
    "criteria": {
      "has_planks": "2026-06-17 23:32:13 +0700"
    },
    "done": true
  },
  "decorative_blocks:recipes/building_blocks/acacia_seat": {
    "criteria": {
      "has_plank": "2026-06-17 23:52:24 +0700"
    },
    "done": true
  },
  "ae2:recipes/misc/network/blocks/crank": {
    "criteria": {
      "has_stick": "2026-06-17 23:35:34 +0700"
    },
    "done": true
  },
  "create:recipes/building_blocks/crafting/logistics/blue_postbox": {
    "criteria": {
      "has_barrel": "2026-06-18 00:08:19 +0700"
    },
    "done": true
  },
  "refurbished_furniture:recipes/misc/constructing/birch_basin": {
    "criteria": {
      "has_birch_planks": "2026-06-17 23:52:08 +0700"
    },
    "done": true
  },
  "refurbished_furniture:recipes/misc/constructing/acacia_toilet": {
    "criteria": {
      "has_acacia_planks": "2026-06-17 23:52:24 +0700"
    },
    "done": true
  },
  "farmersdelight:recipes/food/nether_salad": {
    "criteria": {
      "has_bowl": "2026-06-17 23:47:15 +0700"
    },
    "done": true
  },
  "minecraft:recipes/redstone/crimson_button": {
    "criteria": {
      "has_planks": "2026-06-17 23:52:06 +0700"
    },
    "done": true
  },
  "refurbished_furniture:recipes/misc/constructing/gray_trampoline": {
    "criteria": {
      "has_string": "2026-06-17 23:44:11 +0700"
    },
    "done": true
  },
  "minecraft:recipes/redstone/dark_oak_fence_gate": {
    "criteria": {
      "has_planks": "2026-06-18 00:48:47 +0700"
    },
    "done": true
  },
  "refurbished_furniture:recipes/misc/constructing/jungle_bath": {
    "criteria": {
      "has_jungle_planks": "2026-06-17 23:32:13 +0700"
    },
    "done": true
  },
  "minecraft:recipes/building_blocks/crimson_stairs": {
    "criteria": {
      "has_planks": "2026-06-17 23:52:06 +0700"
    },
    "done": true
  },
  "minecraft:recipes/redstone/dark_oak_trapdoor": {
    "criteria": {
      "has_planks": "2026-06-18 00:48:47 +0700"
    },
    "done": true
  },
  "create:recipes/building_blocks/crafting/kinetics/brown_seat": {
    "criteria": {
      "has_wool": "2026-06-17 23:39:39 +0700"
    },
    "done": true
  },
  "minecraft:recipes/decorations/brown_carpet": {
    "criteria": {
      "has_brown_wool": "2026-06-17 23:39:39 +0700"
    },
    "done": true
  },
  "antiblocksrechiseled:recipes/building_blocks/wool_lime": {
    "criteria": {
      "has_wool": "2026-06-17 23:57:56 +0700"
    },
    "done": true
  },
  "supplementaries:recipes/flags/flag_brown": {
    "criteria": {
      "has_stick": "2026-06-17 23:35:34 +0700"
    },
    "done": true
  },
  "refurbished_furniture:recipes/misc/constructing/crimson_crate": {
    "criteria": {
      "has_crimson_planks": "2026-06-17 23:52:06 +0700"
    },
    "done": true
  },
  "farmersdelight:recipes/combat/flint_knife": {
    "criteria": {
      "has_stick": "2026-06-17 23:35:34 +0700"
    },
    "done": true
  },
  "supplementaries:recipes/flower_box": {
    "criteria": {
      "minecraft:wooden_slabs": "2026-06-18 00:08:14 +0700"
    },
    "done": true
  },
  "create:cardboard": {
    "criteria": {
      "0": "2026-06-18 01:05:30 +0700"
    },
    "done": true
  },
  "antiblocksrechiseled:recipes/building_blocks/wool_blue": {
    "criteria": {
      "has_wool": "2026-06-17 23:57:56 +0700"
    },
    "done": true
  },
  "create:recipes/building_blocks/crafting/logistics/magenta_table_cloth": {
    "criteria": {
      "has_wool": "2026-06-17 23:39:39 +0700"
    },
    "done": true
  },
  "create:recipes/building_blocks/crafting/kinetics/gray_seat": {
    "criteria": {
      "has_wool": "2026-06-17 23:39:39 +0700"
    },
    "done": true
  },
  "ceramicbucket:recipes/misc/ceramic_bucket": {
    "criteria": {
      "has_clay": "2026-06-18 00:14:51 +0700"
    },
    "done": true
  },
  "antiblocksrechiseled:recipes/building_blocks/wool_magenta": {
    "criteria": {
      "has_wool": "2026-06-17 23:57:56 +0700"
    },
    "done": true
  },
  "minecraft:recipes/misc/bowl": {
    "criteria": {
      "has_the_recipe": "2026-06-17 23:56:49 +0700"
    },
    "done": true
  },
  "minecraft:recipes/building_blocks/bricks": {
    "criteria": {
      "has_brick": "2026-06-18 01:02:01 +0700"
    },
    "done": true
  },
  "minecraft:recipes/decorations/painting": {
    "criteria": {
      "has_wool": "2026-06-17 23:39:39 +0700"
    },
    "done": true
  },
  "minecraft:recipes/redstone/acacia_trapdoor": {
    "criteria": {
      "has_planks": "2026-06-17 23:52:24 +0700"
    },
    "done": true
  },
  "refurbished_furniture:recipes/misc/constructing/birch_chair": {
    "criteria": {
      "has_birch_planks": "2026-06-17 23:52:08 +0700"
    },
    "done": true
  },
  "create:recipes/building_blocks/crafting/kinetics/orange_seat": {
    "criteria": {
      "has_wool": "2026-06-17 23:39:39 +0700"
    },
    "done": true
  },
  "supplementaries:recipes/sign_post_birch": {
    "criteria": {
      "has_the_recipe": "2026-06-17 23:52:08 +0700"
    },
    "done": true
  },
  "minecraft:recipes/tools/fishing_rod": {
    "criteria": {
      "has_string": "2026-06-17 23:44:11 +0700"
    },
    "done": true
  },
  "minecraft:recipes/redstone/dark_oak_button": {
    "criteria": {
      "has_planks": "2026-06-18 00:48:47 +0700"
    },
    "done": true
  },
  "antiblocksrechiseled:recipes/building_blocks/wool_light_gray": {
    "criteria": {
      "has_wool": "2026-06-17 23:57:56 +0700"
    },
    "done": true
  },
  "decorative_blocks:recipes/building_blocks/acacia_support": {
    "criteria": {
      "has_plank": "2026-06-17 23:52:24 +0700"
    },
    "done": true
  },
  "refurbished_furniture:recipes/misc/constructing/lime_trampoline": {
    "criteria": {
      "has_string": "2026-06-17 23:44:11 +0700"
    },
    "done": true
  },
  "create:recipes/misc/crafting/logistics/stock_link": {
    "criteria": {
      "has_item": "2026-06-18 01:05:30 +0700"
    },
    "done": true
  },
  "refurbished_furniture:recipes/misc/constructing/dark_oak_bath": {
    "criteria": {
      "has_dark_oak_planks": "2026-06-18 00:48:47 +0700"
    },
    "done": true
  },
  "immersiveengineering:recipes/misc/crafting/alloybrick_from_slab": {
    "criteria": {
      "has_alloybrick": "2026-06-18 01:02:07 +0700"
    },
    "done": true
  },
  "refurbished_furniture:recipes/misc/constructing/crimson_bath": {
    "criteria": {
      "has_crimson_planks": "2026-06-17 23:52:06 +0700"
    },
    "done": true
  },
  "refurbished_furniture:recipes/misc/constructing/black_trampoline": {
    "criteria": {
      "has_string": "2026-06-17 23:44:11 +0700"
    },
    "done": true
  },
  "supplementaries:recipes/bellows": {
    "criteria": {
      "minecraft:wooden_slabs": "2026-06-18 00:08:14 +0700"
    },
    "done": true
  },
  "minecraft:recipes/redstone/jungle_button": {
    "criteria": {
      "has_planks": "2026-06-17 23:32:13 +0700"
    },
    "done": true
  },
  "immersiveengineering:recipes/misc/crafting/blastbrick": {
    "criteria": {
      "has_item": "2026-06-18 01:02:01 +0700"
    },
    "done": true
  },
  "minecraft:husbandry/root": {
    "criteria": {
      "consumed_item": "2026-06-17 23:47:15 +0700"
    },
    "done": true
  },
  "minecraft:recipes/redstone/crimson_trapdoor": {
    "criteria": {
      "has_planks": "2026-06-17 23:52:06 +0700"
    },
    "done": true
  },
  "minecraft:recipes/decorations/white_carpet": {
    "criteria": {
      "has_white_wool": "2026-06-17 23:57:56 +0700"
    },
    "done": true
  },
  "refurbished_furniture:recipes/misc/constructing/jungle_chair": {
    "criteria": {
      "has_jungle_planks": "2026-06-17 23:32:13 +0700"
    },
    "done": true
  },
  "botania:main/tiny_potato_pet": {
    "criteria": {
      "code_triggered": "2026-06-17 23:41:50 +0700"
    },
    "done": true
  },
  "create:recipes/building_blocks/crafting/logistics/purple_postbox": {
    "criteria": {
      "has_barrel": "2026-06-18 00:08:19 +0700"
    },
    "done": true
  },
  "minecraft:recipes/redstone/acacia_fence_gate": {
    "criteria": {
      "has_planks": "2026-06-17 23:52:24 +0700"
    },
    "done": true
  },
  "refurbished_furniture:recipes/misc/constructing/dark_oak_kitchen_storage_cabinet": {
    "criteria": {
      "has_dark_oak_planks": "2026-06-18 00:48:47 +0700"
    },
    "done": true
  },
  "refurbished_furniture:recipes/misc/constructing/cherry_lattice_fence": {
    "criteria": {
      "has_stick": "2026-06-17 23:35:34 +0700"
    },
    "done": true
  },
  "minecraft:recipes/building_blocks/spruce_slab": {
    "criteria": {
      "has_planks": "2026-06-17 23:38:11 +0700"
    },
    "done": true
  },
  "supplementaries:recipes/soap/blackboard": {
    "criteria": {
      "has_soap": "2026-06-18 00:13:08 +0700"
    },
    "done": true
  },
  "refurbished_furniture:recipes/misc/constructing/spruce_cutting_board": {
    "criteria": {
      "has_spruce_planks": "2026-06-17 23:38:11 +0700"
    },
    "done": true
  },
  "minecraft:recipes/redstone/jungle_fence_gate": {
    "criteria": {
      "has_planks": "2026-06-17 23:32:13 +0700"
    },
    "done": true
  },
  "minecraft:recipes/decorations/dark_oak_fence": {
    "criteria": {
      "has_planks": "2026-06-18 00:48:47 +0700"
    },
    "done": true
  },
  "create:recipes/building_blocks/crafting/logistics/light_blue_table_cloth": {
    "criteria": {
      "has_wool": "2026-06-17 23:39:39 +0700"
    },
    "done": true
  },
  "refurbished_furniture:recipes/misc/constructing/crimson_kitchen_sink": {
    "criteria": {
      "has_crimson_planks": "2026-06-17 23:52:06 +0700"
    },
    "done": true
  },
  "supplementaries:recipes/flags/flag_blue": {
    "criteria": {
      "has_stick": "2026-06-17 23:35:34 +0700"
    },
    "done": true
  },
  "refurbished_furniture:recipes/misc/constructing/jungle_drawer": {
    "criteria": {
      "has_jungle_planks": "2026-06-17 23:32:13 +0700"
    },
    "done": true
  },
  "create:recipes/building_blocks/crafting/logistics/white_table_cloth": {
    "criteria": {
      "has_wool": "2026-06-17 23:39:39 +0700"
    },
    "done": true
  },
  "create:recipes/building_blocks/crafting/logistics/gray_table_cloth": {
    "criteria": {
      "has_wool": "2026-06-17 23:39:39 +0700"
    },
    "done": true
  },
  "refurbished_furniture:recipes/misc/constructing/jungle_mail_box": {
    "criteria": {
      "has_jungle_planks": "2026-06-17 23:32:13 +0700"
    },
    "done": true
  },
  "refurbished_furniture:recipes/misc/constructing/warped_lattice_fence_gate": {
    "criteria": {
      "has_stick": "2026-06-17 23:35:34 +0700"
    },
    "done": true
  },
  "supplementaries:recipes/daub_frame": {
    "criteria": {
      "forge:rods/wooden": "2026-06-17 23:35:34 +0700"
    },
    "done": true
  },
  "refurbished_furniture:recipes/misc/constructing/spruce_basin": {
    "criteria": {
      "has_spruce_planks": "2026-06-17 23:38:11 +0700"
    },
    "done": true
  },
  "refurbished_furniture:recipes/misc/constructing/jungle_basin": {
    "criteria": {
      "has_jungle_planks": "2026-06-17 23:32:13 +0700"
    },
    "done": true
  },
  "create:recipes/building_blocks/crafting/kinetics/black_seat": {
    "criteria": {
      "has_wool": "2026-06-17 23:39:39 +0700"
    },
    "done": true
  },
  "refurbished_furniture:recipes/misc/constructing/acacia_kitchen_cabinetry": {
    "criteria": {
      "has_acacia_planks": "2026-06-17 23:52:24 +0700"
    },
    "done": true
  },
  "create:recipes/misc/crafting/kinetics/fluid_tank": {
    "criteria": {
      "has_item": "2026-06-18 00:08:19 +0700"
    },
    "done": true
  },
  "minecraft:recipes/decorations/white_banner": {
    "criteria": {
      "has_white_wool": "2026-06-17 23:57:56 +0700"
    },
    "done": true
  },
  "fairylights:recipes/fairylights/square_pennant": {
    "criteria": {
      "has_string": "2026-06-17 23:44:11 +0700"
    },
    "done": true
  },
  "farmersdelight:main/use_cutting_board": {
    "criteria": {
      "cutting_board": "2026-06-17 23:43:59 +0700"
    },
    "done": true
  },
  "refurbished_furniture:recipes/misc/constructing/acacia_crate": {
    "criteria": {
      "has_acacia_planks": "2026-06-17 23:52:24 +0700"
    },
    "done": true
  },
  "refurbished_furniture:recipes/misc/constructing/mangrove_lattice_fence": {
    "criteria": {
      "has_stick": "2026-06-17 23:35:34 +0700"
    },
    "done": true
  },
  "supplementaries:recipes/flags/flag_yellow": {
    "criteria": {
      "has_stick": "2026-06-17 23:35:34 +0700"
    },
    "done": true
  },
  "minecraft:recipes/redstone/spruce_door": {
    "criteria": {
      "has_planks": "2026-06-17 23:38:11 +0700"
    },
    "done": true
  },
  "minecraft:recipes/redstone/spruce_fence_gate": {
    "criteria": {
      "has_planks": "2026-06-17 23:38:11 +0700"
    },
    "done": true
  },
  "supplementaries:recipes/flags/flag_light_gray": {
    "criteria": {
      "has_stick": "2026-06-17 23:35:34 +0700"
    },
    "done": true
  },
  "refurbished_furniture:recipes/misc/constructing/crimson_cutting_board": {
    "criteria": {
      "has_crimson_planks": "2026-06-17 23:52:06 +0700"
    },
    "done": true
  },
  "create:recipes/building_blocks/crafting/kinetics/white_seat": {
    "criteria": {
      "has_wool": "2026-06-17 23:39:39 +0700"
    },
    "done": true
  },
  "refurbished_furniture:recipes/misc/constructing/birch_mail_box": {
    "criteria": {
      "has_birch_planks": "2026-06-17 23:52:08 +0700"
    },
    "done": true
  },
  "refurbished_furniture:recipes/misc/constructing/crimson_drawer": {
    "criteria": {
      "has_crimson_planks": "2026-06-17 23:52:06 +0700"
    },
    "done": true
  },
  "refurbished_furniture:recipes/misc/constructing/spruce_desk": {
    "criteria": {
      "has_spruce_planks": "2026-06-17 23:38:11 +0700"
    },
    "done": true
  },
  "refurbished_furniture:recipes/misc/constructing/spruce_storage_cabinet": {
    "criteria": {
      "has_spruce_planks": "2026-06-17 23:38:11 +0700"
    },
    "done": true
  },
  "minecraft:recipes/building_blocks/white_wool_from_string": {
    "criteria": {
      "has_string": "2026-06-17 23:44:11 +0700"
    },
    "done": true
  },
  "refurbished_furniture:recipes/misc/constructing/spruce_chair": {
    "criteria": {
      "has_spruce_planks": "2026-06-17 23:38:11 +0700"
    },
    "done": true
  },
  "minecraft:recipes/redstone/crimson_fence_gate": {
    "criteria": {
      "has_planks": "2026-06-17 23:52:06 +0700"
    },
    "done": true
  },
  "refurbished_furniture:recipes/misc/constructing/acacia_lattice_fence_gate": {
    "criteria": {
      "has_stick": "2026-06-17 23:35:34 +0700"
    },
    "done": true
  },
  "decorative_blocks:recipes/building_blocks/dark_oak_seat": {
    "criteria": {
      "has_plank": "2026-06-18 00:48:47 +0700"
    },
    "done": true
  },
  "supplementaries:recipes/jar": {
    "criteria": {
      "minecraft:wooden_slabs": "2026-06-18 00:08:14 +0700"
    },
    "done": true
  },
  "minecraft:husbandry/plant_seed": {
    "criteria": {
      "berry_good:sweet_berry_bush": "2026-06-18 00:15:13 +0700"
    },
    "done": true
  },
  "create:recipes/building_blocks/crafting/kinetics/lime_seat": {
    "criteria": {
      "has_wool": "2026-06-17 23:39:39 +0700"
    },
    "done": true
  },
  "refurbished_furniture:recipes/misc/constructing/dark_oak_desk": {
    "criteria": {
      "has_dark_oak_planks": "2026-06-18 00:48:47 +0700"
    },
    "done": true
  },
  "minecraft:recipes/decorations/flower_pot": {
    "criteria": {
      "has_brick": "2026-06-18 01:02:01 +0700"
    },
    "done": true
  },
  "minecraft:recipes/redstone/birch_pressure_plate": {
    "criteria": {
      "has_planks": "2026-06-17 23:52:08 +0700"
    },
    "done": true
  },
  "farmersdelight:recipes/decorations/cutting_board": {
    "criteria": {
      "has_stick": "2026-06-17 23:35:34 +0700"
    },
    "done": true
  },
  "minecraft:recipes/building_blocks/spruce_stairs": {
    "criteria": {
      "has_planks": "2026-06-17 23:38:11 +0700"
    },
    "done": true
  },
  "refurbished_furniture:recipes/misc/constructing/spruce_drawer": {
    "criteria": {
      "has_spruce_planks": "2026-06-17 23:38:11 +0700"
    },
    "done": true
  },
  "create:recipes/misc/crafting/kinetics/item_vault": {
    "criteria": {
      "has_item": "2026-06-18 00:08:19 +0700"
    },
    "done": true
  },
  "refurbished_furniture:recipes/misc/constructing/purple_trampoline": {
    "criteria": {
      "has_string": "2026-06-17 23:44:11 +0700"
    },
    "done": true
  },
  "minecraft:recipes/decorations/loom": {
    "criteria": {
      "has_string": "2026-06-17 23:44:11 +0700"
    },
    "done": true
  },
  "minecraft:story/root": {
    "criteria": {
      "crafting_table": "2026-06-17 23:32:16 +0700"
    },
    "done": true
  },
  "create:recipes/building_blocks/crafting/kinetics/yellow_seat": {
    "criteria": {
      "has_wool": "2026-06-17 23:39:39 +0700"
    },
    "done": true
  },
  "supplementaries:recipes/soap/globe": {
    "criteria": {
      "has_soap": "2026-06-18 00:13:08 +0700"
    },
    "done": true
  },
  "create:recipes/building_blocks/crafting/logistics/light_gray_postbox": {
    "criteria": {
      "has_barrel": "2026-06-18 00:08:19 +0700"
    },
    "done": true
  },
  "supplementaries:recipes/flags/flag_lime": {
    "criteria": {
      "has_stick": "2026-06-17 23:35:34 +0700"
    },
    "done": true
  },
  "DataVersion": 3465
}